Workbook

Sheet Cover Page
B2: FINANCIAL ACCOUNTING & ANALYSIS
B4: MAJOR PROJECT REPORT
B6: Industry Study: Paints & Coatings
B8: A Comparative Financial Accounting and Ratio Analysis of Five Listed Indian Paints & Coatings Companies
B9: Berger Paints India Ltd. | Kansai Nerolac Paints Ltd. | Asian Paints Ltd. | Indigo Paints Ltd. | JSW Dulux Ltd. (formerly Akzo Nobel India Ltd.)
B12: Team Members | E12: Company Chosen
B13: Sachi Jain (R012) | E13: Berger Paints India Ltd.
B14: Vidisha Kondinya (R016) | E14: Asian Paints Ltd.
B15: Samruddhi Palodkar (R025) | E15: Indigo Paints Ltd.
B16: Arnav Rathod (R031) | E16: Kansai Nerolac Paints Ltd.
B17: Priyansh Soni (R045) | E17: JSW Dulux Ltd.
B20: MBA Tech (Artificial Intelligence)
B21: SVKM’s NMIMS, Mumbai
B23: Course: Financial Accounting & Analysis (FAA)
B24: Faculty: Dr. Alaknanda Lonare
B25: Academic Year 2026-27 | Submission Date: 15 October 2026

Sheet Berger
A1: Berger Paints India Ltd. - Financial Analysis
A2: Standalone Financial Statements | FY2024–25 & FY2025–26 (FY2023–24 Opening Balances) | Amounts in ₹ Crore Unless Stated | Industry Average: Simple Mean of Five Companies
A4: Financial Statement Analysis
A6: A. Key Financial Figures - Financial Statement Data (₹ Crore) - own company inputs used by the analysis
A7: Line Item | C7: Berger Paints
C8: FY2024-25 | D8: FY2025-26
A9: Inventories (closing stock) | C9: 2206.6 | D9: 2225.6
A10: Trade Receivables (current) | C10: 1124.37 | D10: 1129.27
A11: Cash & Cash Equivalents | C11: 141.39 | D11: 151.94
A12: Bank Balances other than Cash & Cash Equivalents | C12: 224.46 | D12: 55.01
A13: Other Current Assets (investments, loans, other financial & non-financial assets) | C13: 436.98 | D13: 1118.69
A14: Total Current Assets | C14: 4133.8 | D14: 4680.51
A15: Trade Payables | C15: 1569.34 | D15: 1522.26
A16: Short-term Borrowings | C16: 0.39 | D16: 0
A17: Other Current Liabilities & Provisions (incl. current lease liabilities) | C17: 416.03 | D17: 619.85
A18: Total Current Liabilities | C18: 1985.76 | D18: 2142.11
A19: Total Borrowings (interest-bearing debt; excludes lease liabilities) | C19: 0.39 | D19: 0
A20: Total Equity / Shareholders’ Funds | C20: 5681.06 | D20: 6342.9
... A29: Total Lease Liabilities, Ind AS 116 - excluded from Total Borrowings above (memo) | C29: 492.1 | D29: 458.74
A31: Opening Balances - FY2023–24 Closing (Reference Only)
A32: These three FY2023-24 closing figures come from the comparative column already printed in each company’s FY2024-25 annual report (see citations below) and are used only to compute average-balance ratios for FY2024-25 in the tables below - they are not part of the two-year dataset used in the rest of this analysis.
A34: Line Item - As at 31 March 2024 | C34: Berger Paints
A35: Inventories (closing stock) | C35: 2019.43
A36: Total Equity / Shareholders’ Funds | C36: 5005.24
A37: Total Assets | C37: 7581.66
A39: Ratio Analysis - Formula, Company Figures & Industry Average
A40: Methodology: Debt-to-Equity excludes Ind AS 116 lease liabilities; a separate lease-inclusive ratio adds Total Lease Liabilities. The Industry Average is the simple arithmetic mean of the same ratio for the five selected companies, including the company being analysed. Supporting financial data is maintained in the Industry Summary sheet, while company-specific ratios are calculated separately for FY2024–25 and FY2025–26. Ratios based on average balances use FY2023–24 closing balances and FY2024–25 closing balances for FY2024–25, and FY2024–25 and FY2025–26 closing balances for FY2025–26. Materials-Consumption Turnover is used as a proxy for Inventory Turnover because a single consolidated Cost of Goods Sold figure is not available for all companies.
A42: B. Liquidity
C43: FY2024-25 | E43: FY2025-26
A44: Ratio | B44: Formula | C44: Company | D44: Industry Avg | E44: Company | F44: Industry Avg
A45: Current Ratio | B45: Current Assets ÷ Current Liabilities | C45: =C14/C18 -> 2.0817219 | D45: ='Industry Summary'!L48 -> 2.4353778 | E45: =D14/D18 -> 2.1849998 | F45: ='Industry Summary'!L60 -> 2.4275972
A46: Quick Ratio | B46: (Current Assets − Inventories) ÷ Current Liabilities | C46: =(C14-C9)/C18 -> 0.97051003 | D46: ='Industry Summary'!L49 -> 1.5808142 | E46: =(D14-D9)/D18 -> 1.1460242 | F46: ='Industry Summary'!L61 -> 1.6811362
A47: Cash Ratio | B47: (Cash & Cash Equivalents + Other Bank Balances) ÷ Current Liabilities | C47: =(C11+C12)/C18 -> 0.18423677 | D47: ='Industry Summary'!L50 -> 0.15262564 | E47: =(D11+D12)/D18 -> 0.096610351 | F47: ='Industry Summary'!L62 -> 0.11967229
A49: C. Solvency and Leverage
C50: FY2024-25 | E50: FY2025-26
A51: Ratio | B51: Formula | C51: Company | D51: Industry Avg | E51: Company | F51: Industry Avg
A52: Debt-to-Equity | B52: Total Borrowings ÷ Total Equity | C52: =C19/C20 -> 6.8649161e-05 | D52: ='Industry Summary'!L54 -> 0.00042882759 | E52: =D19/D20 -> 0 | F52: ='Industry Summary'!L66 -> 0.011449285
A53: Debt-to-Equity (incl. Lease Liabilities) | B53: (Total Borrowings + Total Lease Liabilities) ÷ Total Equity | C53: =(C19+C29)/C20 -> 0.086689808 | D53: ='Industry Summary'!L55 -> 0.048453003 | E53: =(D19+D29)/D20 -> 0.072323385 | F53: ='Industry Summary'!L67 -> 0.053467726
A55: D. Profitability
C56: FY2024-25 | E56: FY2025-26
A57: Ratio | B57: Formula | C57: Company | D57: Industry Avg | E57: Company | F57: Industry Avg
A58: Net Profit Margin | B58: Net Profit (PAT) ÷ Revenue from Operations | C58: =C26/C22 -> 0.105957 | D58: ='Industry Summary'!L51 -> 0.11618978 | E58: =D26/D22 -> 0.1051487 | F58: ='Industry Summary'!L63 -> 0.19305877
A59: Return on Assets (ROA) - average basis | B59: Net Profit (PAT) ÷ Average Total Assets (average of prior-year & current-year closing balances, both years) | C59: =C26/AVERAGE(C37,C21) -> 0.13675446 | D59: ='Industry Summary'!L52 -> 0.13330559 | E59: =D26/AVERAGE(C21,D21) -> 0.12797741 | F59: ='Industry Summary'!L64 -> 0.20609893
A60: Return on Equity (ROE) - average basis | B60: Net Profit (PAT) ÷ Average Total Equity (average of prior-year & current-year closing balances, both years) | C60: =C26/AVERAGE(C36,C20) -> 0.20166007 | D60: ='Industry Summary'!L53 -> 0.20662056 | E60: =D26/AVERAGE(C20,D20) -> 0.18224612 | F60: ='Industry Summary'!L65 -> 0.33024035
A62: E. Efficiency and Turnover
C63: FY2024-25 | E63: FY2025-26
A64: Ratio | B64: Formula | C64: Company | D64: Industry Avg | E64: Company | F64: Industry Avg
A65: Materials-Consumption Turnover - average basis | B65: Cost of Materials Consumed ÷ Average Inventories (named explicitly as a proxy - none of the three companies discloses a single consolidated COGS line; average of prior-year & current-year closing inventory, both years) | C65: =C23/AVERAGE(C35,C9) -> 2.4859218 | D65: ='Industry Summary'!L56 -> 3.0528356 | E65: =D23/AVERAGE(C9,D9) -> 2.3567529 | F65: ='Industry Summary'!L68 -> 2.9688388
A67: F. Growth - Growth & Profitability Ratios
A68: This section presents Revenue Growth (%) and Operating Profit Margin (%) for FY2024–25 and FY2025–26, using the same standalone basis and five-company Industry Average methodology as the preceding analysis. Revenue Growth (%) = (Current-year Revenue from Operations − Previous-year Revenue from Operations) ÷ Previous-year Revenue from Operations. FY2024–25 growth uses FY2023–24 comparative revenue, while FY2025–26 growth uses FY2024–25 and FY2025–26 figures from the financial data above. Operating Profit Margin (%) = Operating Profit ÷ Revenue from Operations, where Operating Profit = Revenue from Operations − (Total Expenses − Finance Costs). This measure is calculated consistently across all five companies using their reported figures.
A70: Additional Data - FY2023–24 Revenue from Operations (Reference Only)
A71: This FY2023-24 comparative figure is used only as the denominator for the FY2024-25 Revenue Growth (%) row below; it is not part of the two-year (FY2024-25/FY2025-26) dataset used elsewhere in this sheet. See the sourcing notes at the end of this section.
A72: Line Item - FY2023-24 | C72: Berger
A73: Revenue from Operations | C73: 10002.93
A75: Additional Financial Statement Data (₹ Crore, Standalone) - Inputs for Operating Profit Margin
A76: Line Item | C76: Berger
C77: FY2024-25 | D77: FY2025-26
A78: Total Expenses (Standalone P&L, full total incl. Finance Costs & Depreciation) | C78: 8860.69 | D78: 9124.76
A79: Finance Costs (Standalone) | C79: 47.86 | D79: 45.6
A81: Growth and Profitability Ratios - Formulas, Company Figures & Industry Average
A82: Revenue Growth (%) = (Current-year Revenue − Previous-year Revenue) ÷ Previous-year Revenue. Operating Profit Margin (%) = [Revenue − (Total Expenses − Finance Costs)] ÷ Revenue, i.e. Profit from Operations before Other Income, Finance Costs & Exceptional Items, as a % of Revenue. Industry Avg = simple (arithmetic) average of the same ratio across all five companies selected for this project (same methodology as the rest of this sheet).
C84: FY2024-25 | E84: FY2025-26
A85: Ratio | B85: Formula | C85: Company | D85: Industry Avg | E85: Company | F85: Industry Avg
A86: Revenue Growth (%) | B86: (Current-year Revenue − Previous-year Revenue) ÷ Previous-year Revenue | C86: =(C22-C73)/C73 -> 0.016624129 | D86: ='Industry Summary'!L75 -> 0.0055003858 | E86: =(D22-C22)/C22 -> 0.024670525 | F86: ='Industry Summary'!L80 -> 0.0038760262
A87: Operating Profit Margin (%) | B87: [Revenue − (Total Expenses − Finance Costs)] ÷ Revenue | C87: =(C22-(C78-C79))/C22 -> 0.13338191 | D87: ='Industry Summary'!L76 -> 0.13378096 | E87: =(D22-(D78-D79))/D22 -> 0.12868782 | F87: ='Industry Summary'!L81 -> 0.13140019
A89: G. 3-Factor DuPont Analysis - ROE Decomposition
A90: ROE = Net Profit Margin × Asset Turnover × Equity Multiplier. This decomposition explains ROE through profitability, asset efficiency and financial leverage. Asset Turnover and Equity Multiplier use the same average-balance convention as the ROA and ROE calculations above, ensuring consistent year-wise comparisons for FY2024–25 and FY2025–26.
C92: FY2024-25 | E92: FY2025-26
A93: Component | B93: Formula | C93: Company | D93: Industry Avg | E93: Company | F93: Industry Avg
A94: Net Profit Margin | B94: PAT ÷ Revenue | C94: =C26/C22 -> 0.105957 | D94: ='Industry Summary'!L51 -> 0.11618978 | E94: =D26/D22 -> 0.1051487 | F94: ='Industry Summary'!L63 -> 0.19305877
A95: Asset Turnover | B95: Revenue ÷ Average Total Assets | C95: =C22/AVERAGE(C37,C21) -> 1.29066 | D95: ='Industry Summary'!L100 -> 1.1598112 | E95: =D22/AVERAGE(C21,D21) -> 1.2171087 | F95: ='Industry Summary'!L107 -> 1.0467514
A96: Equity Multiplier | B96: Average Total Assets ÷ Average Total Equity | C96: =AVERAGE(C37,C21)/AVERAGE(C36,C20) -> 1.4746142 | D96: ='Industry Summary'!L101 -> 1.530061 | E96: =AVERAGE(C21,D21)/AVERAGE(C20,D20) -> 1.4240491 | F96: ='Industry Summary'!L108 -> 1.4416243
A97: ROE (product) | B97: Net Margin × Asset Turnover × Equity Multiplier | C97: =C94*C95*C96 -> 0.20166007 | D97: =D94*D95*D96 -> 0.20618829 | E97: =E94*E95*E96 -> 0.18224612 | F97: =F94*F95*F96 -> 0.29132998
A98: The Industry Average columns for Net Profit Margin, Asset Turnover and Equity Multiplier are calculated as the simple arithmetic mean of the five companies’ respective ratios, including Berger Paints. Industry Average ROE (product) is the product of these three average components, not the arithmetic mean of the five companies’ ROEs. Therefore, it differs from the direct average ROE: 20.62% versus 20.66% in FY2024–25 and 29.13% versus 33.02% in FY2025–26. The difference is particularly pronounced in FY2025–26 because of JSW Dulux’s exceptional-item-inflated margin. The 5-Factor DuPont analysis below applies the same product-of-averages approach.
A100: H. 5-Factor DuPont Analysis of Return on Equity (Supplementary Analysis, Standalone)
A101: The 5-Factor DuPont model decomposes Return on Equity into five components: Tax Burden, Interest Burden, EBIT Margin, Asset Turnover and Equity Multiplier. Asset Turnover and Equity Multiplier follow the same average-balance convention as the 3-Factor model. The product of all five components reconciles to Net Profit (PAT) ÷ Average Total Equity, the directly calculated ROE. The Reconciliation Difference below verifies this for both financial years.
A103: EBIT is defined here as Profit Before Tax (PBT) + Finance Costs - the standard textbook DuPont definition (“Earnings Before Interest and Tax”), chosen specifically because it makes Interest Burden (PBT ÷ EBIT) a clean, well-behaved ratio and makes the five-factor product reconcile to reported ROE by construction, not by any forced adjustment. Because PBT already includes Other Income and any Exceptional Items, this EBIT (and the EBIT Margin and Interest Burden derived from it) also includes their effect - unlike the “Operating Profit Margin” in the Growth & Profitability Ratios section above, which deliberately excludes Other Income, Finance Costs and Exceptional Items to show recurring operating performance only. The two margins are therefore not the same measure and are not interchangeable: Operating Profit Margin above is the cleaner recurring-operations view; EBIT Margin here is the measure needed for the five-factor ROE decomposition to reconcile exactly.
A105: Factor | B105: Formula | C105: Company | D105: Industry Avg | E105: Company | F105: Industry Avg
A106: Tax Burden | B106: Net Profit (PAT) ÷ Profit Before Tax (PBT) | C106: =C26/C24 -> 0.75310678 | D106: ='Industry Summary'!L116 -> 0.74455076 | E106: =D26/D24 -> 0.76181669 | F106: ='Industry Summary'!L127 -> 0.76399743
A107: Interest Burden | B107: PBT ÷ EBIT (EBIT = PBT + Finance Costs) | C107: =C24/(C24+C79) -> 0.96763154 | D107: ='Industry Summary'!L117 -> 0.97925396 | E107: =D24/(D24+D79) -> 0.96926851 | F107: ='Industry Summary'!L128 -> 0.9817446
A108: EBIT Margin | B108: EBIT ÷ Revenue from Operations | C108: =(C24+C79)/C22 -> 0.14539955 | D108: ='Industry Summary'!L118 -> 0.15948466 | E108: =(D24+D79)/D22 -> 0.14239979 | F108: ='Industry Summary'!L129 -> 0.24689542
A109: Asset Turnover | B109: Revenue ÷ Average Total Assets (as in the 3-Factor DuPont analysis above) | C109: =C95 -> 1.29066 | D109: ='Industry Summary'!L100 -> 1.1598112 | E109: =E95 -> 1.2171087 | F109: ='Industry Summary'!L107 -> 1.0467514
A110: Equity Multiplier | B110: Average Total Assets ÷ Average Total Equity (as in the 3-Factor DuPont analysis above) | C110: =C96 -> 1.4746142 | D110: ='Industry Summary'!L101 -> 1.530061 | E110: =E96 -> 1.4240491 | F110: ='Industry Summary'!L108 -> 1.4416243
A111: 5-Factor DuPont ROE (product) | B111: Tax Burden × Interest Burden × EBIT Margin × Asset Turnover × Equity Multiplier | C111: =C106*C107*C108*C109*C110 -> 0.20166007 | D111: =D106*D107*D108*D109*D110 -> 0.20635007 | E111: =E106*E107*E108*E109*E110 -> 0.18224612 | F111: =F106*F107*F108*F109*F110 -> 0.27944678
A112: Directly-Calculated ROE (existing, above) | B112: Net Profit (PAT) ÷ Average Total Equity - same figure as the Ratio Analysis / 3-Factor DuPont ROE above | C112: =C60 -> 0.20166007 | D112: =D60 -> 0.20662056 | E112: =E60 -> 0.18224612 | F112: =F60 -> 0.33024035
A113: Reconciliation Difference | B113: 5-Factor DuPont ROE − Directly-Calculated ROE (should be ~0.00%) | C113: =C111-C112 -> 0 | D113: =D111-D112 -> -0.00027049493 | E113: =E111-E112 -> 0 | F113: =F111-F112 -> -0.050793571
A114: The Industry Average in the 5-Factor DuPont ROE row is calculated by multiplying the five separately averaged components: Tax Burden, Interest Burden, EBIT Margin, Asset Turnover and Equity Multiplier. This product of averages differs mathematically from the arithmetic mean of the five companies’ individual ROEs, so the Industry Average Reconciliation Difference is non-zero. This is an averaging-order effect, not a formula error, and is particularly pronounced in FY2025–26 because of JSW Dulux’s exceptional-item-driven results. The individual company columns reconcile to their directly calculated ROE, subject only to rounding.
A116: I. Industry Average Comparisons - Company vs Industry Average (data tables and charts)
A117: Ratio | B117: Company FY24-25 | C117: Industry Avg FY24-25 | D117: Company FY25-26 | E117: Industry Avg FY25-26
A118: Current Ratio | B118: =C45 -> 2.0817219 | C118: =D45 -> 2.4353778 | D118: =E45 -> 2.1849998 | E118: =F45 -> 2.4275972
A119: Quick Ratio | B119: =C46 -> 0.97051003 | C119: =D46 -> 1.5808142 | D119: =E46 -> 1.1460242 | E119: =F46 -> 1.6811362
A120: Cash Ratio | B120: =C47 -> 0.18423677 | C120: =D47 -> 0.15262564 | D120: =E47 -> 0.096610351 | E120: =F47 -> 0.11967229
A121: Debt-to-Equity | B121: =C52 -> 6.8649161e-05 | C121: =D52 -> 0.00042882759 | D121: =E52 -> 0 | E121: =F52 -> 0.011449285
A122: D/E incl. Lease | B122: =C53 -> 0.086689808 | C122: =D53 -> 0.048453003 | D122: =E53 -> 0.072323385 | E122: =F53 -> 0.053467726
A147: Ratio | B147: Company FY24-25 | C147: Industry Avg FY24-25 | D147: Company FY25-26 | E147: Industry Avg FY25-26
A148: Net Profit Margin | B148: =C58 -> 0.105957 | C148: =D58 -> 0.11618978 | D148: =E58 -> 0.1051487 | E148: =F58 -> 0.19305877
A149: Return on Assets (ROA) | B149: =C59 -> 0.13675446 | C149: =D59 -> 0.13330559 | D149: =E59 -> 0.12797741 | E149: =F59 -> 0.20609893
A150: Return on Equity (ROE) | B150: =C60 -> 0.20166007 | C150: =D60 -> 0.20662056 | D150: =E60 -> 0.18224612 | E150: =F60 -> 0.33024035
A176: J. Supporting Calculations, Interpretations, Sources and Disclosures
A177: Reporting basis, units and sources - by company (disclosures for the input tables in the Industry Summary sheet)
...

Sheet Kansai Nerolac
A1: Kansai Nerolac Paints Ltd. - Financial Analysis
A2: Standalone Financial Statements | FY2024–25 & FY2025–26 (FY2023–24 Opening Balances) | Amounts in ₹ Crore Unless Stated | Industry Average: Simple Mean of Five Companies
A4: Financial Statement Analysis
A6: A. Key Financial Figures - Financial Statement Data (₹ Crore) - own company inputs used by the analysis
A7: Line Item | C7: Kansai Nerolac
C8: FY2024-25 | D8: FY2025-26
A9: Inventories (closing stock) | C9: 1609.71 | D9: 1492.92
A10: Trade Receivables (current) | C10: 1274.7 | D10: 1379.83
A11: Cash & Cash Equivalents | C11: 85.72 | D11: 184.12
A12: Bank Balances other than Cash & Cash Equivalents | C12: 174.52 | D12: 7.97
A13: Other Current Assets (investments, loans, other financial & non-financial assets) | C13: 2029.11 | D13: 2549.88
A14: Total Current Assets | C14: 5173.76 | D14: 5614.72
A15: Trade Payables | C15: 1023.65 | D15: 1075.42
A16: Short-term Borrowings | C16: 0 | D16: 0
A17: Other Current Liabilities & Provisions (incl. current lease liabilities) | C17: 263.68 | D17: 422.77
A18: Total Current Liabilities | C18: 1287.33 | D18: 1498.19
A19: Total Borrowings (interest-bearing debt; excludes lease liabilities) | C19: 0 | D19: 0
A20: Total Equity / Shareholders’ Funds | C20: 6366.23 | D20: 6695.77
... A29: Total Lease Liabilities, Ind AS 116 - excluded from Total Borrowings above (memo) | C29: 171.2 | D29: 217.2
A31: Opening Balances - FY2023–24 Closing (Reference Only)
A32: These three FY2023-24 closing figures come from the comparative column already printed in each company’s FY2024-25 annual report (see citations below) and are used only to compute average-balance ratios for FY2024-25 in the tables below - they are not part of the two-year dataset used in the rest of this analysis.
A34: Line Item - As at 31 March 2024 | C34: Kansai Nerolac
A35: Inventories (closing stock) | C35: 1616.04
A36: Total Equity / Shareholders’ Funds | C36: 5653.12
A37: Total Assets | C37: 7224.8
A39: Ratio Analysis - Formula, Company Figures & Industry Average
A40: Methodology: Debt-to-Equity excludes Ind AS 116 lease liabilities; a separate lease-inclusive ratio adds Total Lease Liabilities. The Industry Average is the simple arithmetic mean of the same ratio for the five selected companies, including the company being analysed. Supporting financial data is maintained in the Industry Summary sheet, while company-specific ratios are calculated separately for FY2024–25 and FY2025–26. Ratios based on average balances use FY2023–24 closing balances and FY2024–25 closing balances for FY2024–25, and FY2024–25 and FY2025–26 closing balances for FY2025–26. Materials-Consumption Turnover is used as a proxy for Inventory Turnover because a single consolidated Cost of Goods Sold figure is not available for all companies.
A42: B. Liquidity
C43: FY2024-25 | E43: FY2025-26
A44: Ratio | B44: Formula | C44: Company | D44: Industry Avg | E44: Company | F44: Industry Avg
A45: Current Ratio | B45: Current Assets ÷ Current Liabilities | C45: =C14/C18 -> 4.018985 | D45: ='Industry Summary'!L48 -> 2.4353778 | E45: =D14/D18 -> 3.7476689 | F45: ='Industry Summary'!L60 -> 2.4275972
A46: Quick Ratio | B46: (Current Assets − Inventories) ÷ Current Liabilities | C46: =(C14-C9)/C18 -> 2.7685597 | D46: ='Industry Summary'!L49 -> 1.5808142 | E46: =(D14-D9)/D18 -> 2.7511864 | F46: ='Industry Summary'!L61 -> 1.6811362
A47: Cash Ratio | B47: (Cash & Cash Equivalents + Other Bank Balances) ÷ Current Liabilities | C47: =(C11+C12)/C18 -> 0.20215485 | D47: ='Industry Summary'!L50 -> 0.15262564 | E47: =(D11+D12)/D18 -> 0.12821471 | F47: ='Industry Summary'!L62 -> 0.11967229
A49: C. Solvency and Leverage
C50: FY2024-25 | E50: FY2025-26
A51: Ratio | B51: Formula | C51: Company | D51: Industry Avg | E51: Company | F51: Industry Avg
A52: Debt-to-Equity | B52: Total Borrowings ÷ Total Equity | C52: =C19/C20 -> 0 | D52: ='Industry Summary'!L54 -> 0.00042882759 | E52: =D19/D20 -> 0 | F52: ='Industry Summary'!L66 -> 0.011449285
A53: Debt-to-Equity (incl. Lease Liabilities) | B53: (Total Borrowings + Total Lease Liabilities) ÷ Total Equity | C53: =(C19+C29)/C20 -> 0.026891897 | D53: ='Industry Summary'!L55 -> 0.048453003 | E53: =(D19+D29)/D20 -> 0.03243839 | F53: ='Industry Summary'!L67 -> 0.053467726
A55: D. Profitability
C56: FY2024-25 | E56: FY2025-26
A57: Ratio | B57: Formula | C57: Company | D57: Industry Avg | E57: Company | F57: Industry Avg
A58: Net Profit Margin | B58: Net Profit (PAT) ÷ Revenue from Operations | C58: =C26/C22 -> 0.13622509 | D58: ='Industry Summary'!L51 -> 0.11618978 | E58: =D26/D22 -> 0.080091947 | F58: ='Industry Summary'!L63 -> 0.19305877
A59: Return on Assets (ROA) - average basis | B59: Net Profit (PAT) ÷ Average Total Assets (average of prior-year & current-year closing balances, both years) | C59: =C26/AVERAGE(C37,C21) -> 0.13442639 | D59: ='Industry Summary'!L52 -> 0.13330559 | E59: =D26/AVERAGE(C21,D21) -> 0.075097696 | F59: ='Industry Summary'!L64 -> 0.20609893
A60: Return on Equity (ROE) - average basis | B60: Net Profit (PAT) ÷ Average Total Equity (average of prior-year & current-year closing balances, both years) | C60: =C26/AVERAGE(C36,C20) -> 0.16993265 | D60: ='Industry Summary'!L53 -> 0.20662056 | E60: =D26/AVERAGE(C20,D20) -> 0.094908896 | F60: ='Industry Summary'!L65 -> 0.33024035
A62: E. Efficiency and Turnover
C63: FY2024-25 | E63: FY2025-26
A64: Ratio | B64: Formula | C64: Company | D64: Industry Avg | E64: Company | F64: Industry Avg
A65: Materials-Consumption Turnover - average basis | B65: Cost of Materials Consumed ÷ Average Inventories (named explicitly as a proxy - none of the three companies discloses a single consolidated COGS line; average of prior-year & current-year closing inventory, both years) | C65: =C23/AVERAGE(C35,C9) -> 2.7019267 | D65: ='Industry Summary'!L56 -> 3.0528356 | E65: =D23/AVERAGE(C9,D9) -> 2.8248293 | F65: ='Industry Summary'!L68 -> 2.9688388
A67: F. Growth - Growth & Profitability Ratios
A68: This section presents Revenue Growth (%) and Operating Profit Margin (%) for FY2024–25 and FY2025–26, using the same standalone basis and five-company Industry Average methodology as the preceding analysis. Revenue Growth (%) = (Current-year Revenue from Operations − Previous-year Revenue from Operations) ÷ Previous-year Revenue from Operations. FY2024–25 growth uses FY2023–24 comparative revenue, while FY2025–26 growth uses FY2024–25 and FY2025–26 figures from the financial data above. Operating Profit Margin (%) = Operating Profit ÷ Revenue from Operations, where Operating Profit = Revenue from Operations − (Total Expenses − Finance Costs). This measure is calculated consistently across all five companies using their reported figures.
A70: Additional Data - FY2023–24 Revenue from Operations (Reference Only)
A71: This FY2023-24 comparative figure is used only as the denominator for the FY2024-25 Revenue Growth (%) row below; it is not part of the two-year (FY2024-25/FY2025-26) dataset used elsewhere in this sheet. See the sourcing notes at the end of this section.
A72: Line Item - FY2023-24 | C72: Kansai Nerolac
A73: Revenue from Operations | C73: 7393.3
A75: Additional Financial Statement Data (₹ Crore, Standalone) - Inputs for Operating Profit Margin
A76: Line Item | C76: Kansai Nerolac
C77: FY2024-25 | D77: FY2025-26
A78: Total Expenses (Standalone P&L, full total incl. Finance Costs & Depreciation) | C78: 6731.35 | D78: 6992.78
A79: Finance Costs (Standalone) | C79: 15.09 | D79: 18.41
A81: Growth and Profitability Ratios - Formulas, Company Figures & Industry Average
A82: Revenue Growth (%) = (Current-year Revenue − Previous-year Revenue) ÷ Previous-year Revenue. Operating Profit Margin (%) = [Revenue − (Total Expenses − Finance Costs)] ÷ Revenue, i.e. Profit from Operations before Other Income, Finance Costs & Exceptional Items, as a % of Revenue. Industry Avg = simple (arithmetic) average of the same ratio across all five companies selected for this project (same methodology as the rest of this sheet).
C84: FY2024-25 | E84: FY2025-26
A85: Ratio | B85: Formula | C85: Company | D85: Industry Avg | E85: Company | F85: Industry Avg
A86: Revenue Growth (%) | B86: (Current-year Revenue − Previous-year Revenue) ÷ Previous-year Revenue | C86: =(C22-C73)/C73 -> 0.013986988 | D86: ='Industry Summary'!L75 -> 0.0055003858 | E86: =(D22-C22)/C22 -> 0.032350191 | F86: ='Industry Summary'!L80 -> 0.0038760262
A87: Operating Profit Margin (%) | B87: [Revenue − (Total Expenses − Finance Costs)] ÷ Revenue | C87: =(C22-(C78-C79))/C22 -> 0.10410567 | D87: ='Industry Summary'!L76 -> 0.13378096 | E87: =(D22-(D78-D79))/D22 -> 0.098828953 | F87: ='Industry Summary'!L81 -> 0.13140019
A89: G. 3-Factor DuPont Analysis - ROE Decomposition
A90: ROE = Net Profit Margin × Asset Turnover × Equity Multiplier. This decomposition explains ROE through profitability, asset efficiency and financial leverage. Asset Turnover and Equity Multiplier use the same average-balance convention as the ROA and ROE calculations above, ensuring consistent year-wise comparisons for FY2024–25 and FY2025–26.
C92: FY2024-25 | E92: FY2025-26
A93: Component | B93: Formula | C93: Company | D93: Industry Avg | E93: Company | F93: Industry Avg
A94: Net Profit Margin | B94: PAT ÷ Revenue | C94: =C26/C22 -> 0.13622509 | D94: ='Industry Summary'!L51 -> 0.11618978 | E94: =D26/D22 -> 0.080091947 | F94: ='Industry Summary'!L63 -> 0.19305877
A95: Asset Turnover | B95: Revenue ÷ Average Total Assets | C95: =C22/AVERAGE(C37,C21) -> 0.98679614 | D95: ='Industry Summary'!L100 -> 1.1598112 | E95: =D22/AVERAGE(C21,D21) -> 0.93764353 | F95: ='Industry Summary'!L107 -> 1.0467514
A96: Equity Multiplier | B96: Average Total Assets ÷ Average Total Equity | C96: =AVERAGE(C37,C21)/AVERAGE(C36,C20) -> 1.2641316 | D96: ='Industry Summary'!L101 -> 1.530061 | E96: =AVERAGE(C21,D21)/AVERAGE(C20,D20) -> 1.2638057 | F96: ='Industry Summary'!L108 -> 1.4416243
A97: ROE (product) | B97: Net Margin × Asset Turnover × Equity Multiplier | C97: =C94*C95*C96 -> 0.16993265 | D97: =D94*D95*D96 -> 0.20618829 | E97: =E94*E95*E96 -> 0.094908896 | F97: =F94*F95*F96 -> 0.29132998
A98: The Industry Average columns for Net Profit Margin, Asset Turnover and Equity Multiplier are calculated as the simple arithmetic mean of the five companies’ respective ratios, including Kansai Nerolac Paints. Industry Average ROE (product) is the product of these three average components, not the arithmetic mean of the five companies’ ROEs. Therefore, it differs from the direct average ROE: 20.62% versus 20.66% in FY2024–25 and 29.13% versus 33.02% in FY2025–26. The difference is particularly pronounced in FY2025–26 because of JSW Dulux’s exceptional-item-inflated margin. The 5-Factor DuPont analysis below applies the same product-of-averages approach.
A100: H. 5-Factor DuPont Analysis of Return on Equity (Supplementary Analysis, Standalone)
A101: The 5-Factor DuPont model decomposes Return on Equity into five components: Tax Burden, Interest Burden, EBIT Margin, Asset Turnover and Equity Multiplier. Asset Turnover and Equity Multiplier follow the same average-balance convention as the 3-Factor model. The product of all five components reconciles to Net Profit (PAT) ÷ Average Total Equity, the directly calculated ROE. The Reconciliation Difference below verifies this for both financial years.
A103: EBIT is defined here as Profit Before Tax (PBT) + Finance Costs - the standard textbook DuPont definition (“Earnings Before Interest and Tax”), chosen specifically because it makes Interest Burden (PBT ÷ EBIT) a clean, well-behaved ratio and makes the five-factor product reconcile to reported ROE by construction, not by any forced adjustment. Because PBT already includes Other Income and any Exceptional Items, this EBIT (and the EBIT Margin and Interest Burden derived from it) also includes their effect - unlike the “Operating Profit Margin” in the Growth & Profitability Ratios section above, which deliberately excludes Other Income, Finance Costs and Exceptional Items to show recurring operating performance only. The two margins are therefore not the same measure and are not interchangeable: Operating Profit Margin above is the cleaner recurring-operations view; EBIT Margin here is the measure needed for the five-factor ROE decomposition to reconcile exactly.
A105: Factor | B105: Formula | C105: Company | D105: Industry Avg | E105: Company | F105: Industry Avg
A106: Tax Burden | B106: Net Profit (PAT) ÷ Profit Before Tax (PBT) | C106: =C26/C24 -> 0.73650125 | D106: ='Industry Summary'!L116 -> 0.74455076 | E106: =D26/D24 -> 0.73949249 | F106: ='Industry Summary'!L127 -> 0.76399743
A107: Interest Burden | B107: PBT ÷ EBIT (EBIT = PBT + Finance Costs) | C107: =C24/(C24+C79) -> 0.9892345 | D107: ='Industry Summary'!L117 -> 0.97925396 | E107: =D24/(D24+D79) -> 0.97850856 | F107: ='Industry Summary'!L128 -> 0.9817446
A108: EBIT Margin | B108: EBIT ÷ Revenue from Operations | C108: =(C24+C79)/C22 -> 0.18697535 | D108: ='Industry Summary'!L118 -> 0.15948466 | E108: =(D24+D79)/D22 -> 0.11068543 | F108: ='Industry Summary'!L129 -> 0.24689542
A109: Asset Turnover | B109: Revenue ÷ Average Total Assets (as in the 3-Factor DuPont analysis above) | C109: =C95 -> 0.98679614 | D109: ='Industry Summary'!L100 -> 1.1598112 | E109: =E95 -> 0.93764353 | F109: ='Industry Summary'!L107 -> 1.0467514
A110: Equity Multiplier | B110: Average Total Assets ÷ Average Total Equity (as in the 3-Factor DuPont analysis above) | C110: =C96 -> 1.2641316 | D110: ='Industry Summary'!L101 -> 1.530061 | E110: =E96 -> 1.2638057 | F110: ='Industry Summary'!L108 -> 1.4416243
A111: 5-Factor DuPont ROE (product) | B111: Tax Burden × Interest Burden × EBIT Margin × Asset Turnover × Equity Multiplier | C111: =C106*C107*C108*C109*C110 -> 0.16993265 | D111: =D106*D107*D108*D109*D110 -> 0.20635007 | E111: =E106*E107*E108*E109*E110 -> 0.094908896 | F111: =F106*F107*F108*F109*F110 -> 0.27944678
A112: Directly-Calculated ROE (existing, above) | B112: Net Profit (PAT) ÷ Average Total Equity - same figure as the Ratio Analysis / 3-Factor DuPont ROE above | C112: =C60 -> 0.16993265 | D112: =D60 -> 0.20662056 | E112: =E60 -> 0.094908896 | F112: =F60 -> 0.33024035
A113: Reconciliation Difference | B113: 5-Factor DuPont ROE − Directly-Calculated ROE (should be ~0.00%) | C113: =C111-C112 -> 0 | D113: =D111-D112 -> -0.00027049493 | E113: =E111-E112 -> 0 | F113: =F111-F112 -> -0.050793571
A114: The Industry Average in the 5-Factor DuPont ROE row is calculated by multiplying the five separately averaged components: Tax Burden, Interest Burden, EBIT Margin, Asset Turnover and Equity Multiplier. This product of averages differs mathematically from the arithmetic mean of the five companies’ individual ROEs, so the Industry Average Reconciliation Difference is non-zero. This is an averaging-order effect, not a formula error, and is particularly pronounced in FY2025–26 because of JSW Dulux’s exceptional-item-driven results. The individual company columns reconcile to their directly calculated ROE, subject only to rounding.
A116: I. Industry Average Comparisons - Company vs Industry Average (data tables and charts)
A117: Ratio | B117: Company FY24-25 | C117: Industry Avg FY24-25 | D117: Company FY25-26 | E117: Industry Avg FY25-26
A118: Current Ratio | B118: =C45 -> 4.018985 | C118: =D45 -> 2.4353778 | D118: =E45 -> 3.7476689 | E118: =F45 -> 2.4275972
A119: Quick Ratio | B119: =C46 -> 2.7685597 | C119: =D46 -> 1.5808142 | D119: =E46 -> 2.7511864 | E119: =F46 -> 1.6811362
A120: Cash Ratio | B120: =C47 -> 0.20215485 | C120: =D47 -> 0.15262564 | D120: =E47 -> 0.12821471 | E120: =F47 -> 0.11967229
A121: Debt-to-Equity | B121: =C52 -> 0 | C121: =D52 -> 0.00042882759 | D121: =E52 -> 0 | E121: =F52 -> 0.011449285
A122: D/E incl. Lease | B122: =C53 -> 0.026891897 | C122: =D53 -> 0.048453003 | D122: =E53 -> 0.03243839 | E122: =F53 -> 0.053467726
A143: Ratio | B143: Company FY24-25 | C143: Industry Avg FY24-25 | D143: Company FY25-26 | E143: Industry Avg FY25-26
A144: Net Profit Margin | B144: =C58 -> 0.13622509 | C144: =D58 -> 0.11618978 | D144: =E58 -> 0.080091947 | E144: =F58 -> 0.19305877
A145: Return on Assets (ROA) | B145: =C59 -> 0.13442639 | C145: =D59 -> 0.13330559 | D145: =E59 -> 0.075097696 | E145: =F59 -> 0.20609893
A146: Return on Equity (ROE) | B146: =C60 -> 0.16993265 | C146: =D60 -> 0.20662056 | D146: =E60 -> 0.094908896 | E146: =F60 -> 0.33024035
A168: J. Supporting Calculations, Interpretations, Sources and Disclosures
A169: Reporting basis, units and sources - by company (disclosures for the input tables in the Industry Summary sheet)
...

Sheet Asian Paints
A1: Asian Paints Ltd. - Financial Analysis
A2: Standalone Financial Statements | FY2024–25 & FY2025–26 (FY2023–24 Opening Balances) | Amounts in ₹ Crore Unless Stated | Industry Average: Simple Mean of Five Companies
A4: Financial Statement Analysis
A6: A. Key Financial Figures - Financial Statement Data (₹ Crore) - own company inputs used by the analysis
A7: Line Item | C7: Asian Paints
C8: FY2024-25 | D8: FY2025-26
A9: Inventories (closing stock) | C9: 5848.23 | D9: 4824.74
A10: Trade Receivables (current) | C10: 3197.55 | D10: 3227.71
A11: Cash & Cash Equivalents | C11: 176.19 | D11: 395.38
A12: Bank Balances other than Cash & Cash Equivalents | C12: 26.09 | D12: 50.96
A13: Other Current Assets (investments, loans, other financial & non-financial assets) | C13: 5039.88 | D13: 8757.44
A14: Total Current Assets | C14: 14287.94 | D14: 17256.23
A15: Trade Payables | C15: 3123.69 | D15: 3114.48
A16: Short-term Borrowings | C16: 2.15 | D16: 340.73
A17: Other Current Liabilities & Provisions (incl. current lease liabilities) | C17: 3090.36 | D17: 3550.67
A18: Total Current Liabilities | C18: 6216.2 | D18: 7005.88
A19: Total Borrowings (interest-bearing debt; excludes lease liabilities) | C19: 39.4 | D19: 1189.67
A20: Total Equity / Shareholders’ Funds | C20: 18983.48 | D20: 20781.56
... A29: Total Lease Liabilities, Ind AS 116 - excluded from Total Borrowings above (memo) | C29: 1159.42 | D29: 1179.29
A31: Opening Balances - FY2023–24 Closing (Reference Only)
A32: These three FY2023-24 closing figures come from the comparative column already printed in each company’s FY2024-25 annual report (see citations below) and are used only to compute average-balance ratios for FY2024-25 in the tables below - they are not part of the two-year dataset used in the rest of this analysis.
A34: Line Item - As at 31 March 2024 | C34: Asian Paints
A35: Inventories (closing stock) | C35: 5155.59
A36: Total Equity / Shareholders’ Funds | C36: 18288.66
A37: Total Assets | C37: 26035.64
A39: Ratio Analysis - Formula, Company Figures & Industry Average
A40: Methodology: Debt-to-Equity excludes Ind AS 116 lease liabilities; a separate lease-inclusive ratio adds Total Lease Liabilities. The Industry Average is the simple arithmetic mean of the same ratio for the five selected companies, including the company being analysed. Supporting financial data is maintained in the Industry Summary sheet, while company-specific ratios are calculated separately for FY2024–25 and FY2025–26. Ratios based on average balances use FY2023–24 closing balances and FY2024–25 closing balances for FY2024–25, and FY2024–25 and FY2025–26 closing balances for FY2025–26. Materials-Consumption Turnover is used as a proxy for Inventory Turnover because a single consolidated Cost of Goods Sold figure is not available for all companies.
A42: B. Liquidity
C43: FY2024-25 | E43: FY2025-26
A44: Ratio | B44: Formula | C44: Company | D44: Industry Avg | E44: Company | F44: Industry Avg
A45: Current Ratio | B45: Current Assets ÷ Current Liabilities | C45: =C14/C18 -> 2.2985007 | D45: ='Industry Summary'!L48 -> 2.4353778 | E45: =D14/D18 -> 2.4631067 | F45: ='Industry Summary'!L60 -> 2.4275972
A46: Quick Ratio | B46: (Current Assets − Inventories) ÷ Current Liabilities | C46: =(C14-C9)/C18 -> 1.357696 | D46: ='Industry Summary'!L49 -> 1.5808142 | E46: =(D14-D9)/D18 -> 1.7744366 | F46: ='Industry Summary'!L61 -> 1.6811362
A47: Cash Ratio | B47: (Cash & Cash Equivalents + Other Bank Balances) ÷ Current Liabilities | C47: =(C11+C12)/C18 -> 0.032540781 | D47: ='Industry Summary'!L50 -> 0.15262564 | E47: =(D11+D12)/D18 -> 0.063709341 | F47: ='Industry Summary'!L62 -> 0.11967229
A49: C. Solvency and Leverage
C50: FY2024-25 | E50: FY2025-26
A51: Ratio | B51: Formula | C51: Company | D51: Industry Avg | E51: Company | F51: Industry Avg
A52: Debt-to-Equity | B52: Total Borrowings ÷ Total Equity | C52: =C19/C20 -> 0.0020754888 | D52: ='Industry Summary'!L54 -> 0.00042882759 | E52: =D19/D20 -> 0.057246424 | F52: ='Industry Summary'!L66 -> 0.011449285
A53: Debt-to-Equity (incl. Lease Liabilities) | B53: (Total Borrowings + Total Lease Liabilities) ÷ Total Equity | C53: =(C19+C29)/C20 -> 0.063150697 | D53: ='Industry Summary'!L55 -> 0.048453003 | E53: =(D19+D29)/D20 -> 0.11399337 | F53: ='Industry Summary'!L67 -> 0.053467726
A55: D. Profitability
C56: FY2024-25 | E56: FY2025-26
A57: Ratio | B57: Formula | C57: Company | D57: Industry Avg | E57: Company | F57: Industry Avg
A58: Net Profit Margin | B58: Net Profit (PAT) ÷ Revenue from Operations | C58: =C26/C22 -> 0.12130486 | D58: ='Industry Summary'!L51 -> 0.11618978 | E58: =D26/D22 -> 0.13793441 | F58: ='Industry Summary'!L63 -> 0.19305877
A59: Return on Assets (ROA) - average basis | B59: Net Profit (PAT) ÷ Average Total Assets (average of prior-year & current-year closing balances, both years) | C59: =C26/AVERAGE(C37,C21) -> 0.13607763 | D59: ='Industry Summary'!L52 -> 0.13330559 | E59: =D26/AVERAGE(C21,D21) -> 0.14960757 | F59: ='Industry Summary'!L64 -> 0.20609893
A60: Return on Equity (ROE) - average basis | B60: Net Profit (PAT) ÷ Average Total Equity (average of prior-year & current-year closing balances, both years) | C60: =C26/AVERAGE(C36,C20) -> 0.19236245 | D60: ='Industry Summary'!L53 -> 0.20662056 | E60: =D26/AVERAGE(C20,D20) -> 0.21346238 | F60: ='Industry Summary'!L65 -> 0.33024035
A62: E. Efficiency and Turnover
C63: FY2024-25 | E63: FY2025-26
A64: Ratio | B64: Formula | C64: Company | D64: Industry Avg | E64: Company | F64: Industry Avg
A65: Materials-Consumption Turnover - average basis | B65: Cost of Materials Consumed ÷ Average Inventories (named explicitly as a proxy - none of the three companies discloses a single consolidated COGS line; average of prior-year & current-year closing inventory, both years) | C65: =C23/AVERAGE(C35,C9) -> 2.4061317 | D65: ='Industry Summary'!L56 -> 3.0528356 | E65: =D23/AVERAGE(C9,D9) -> 2.37437 | F65: ='Industry Summary'!L68 -> 2.9688388
A67: F. Growth - Growth & Profitability Ratios
A68: This section presents Revenue Growth (%) and Operating Profit Margin (%) for FY2024–25 and FY2025–26, using the same standalone basis and five-company Industry Average methodology as the preceding analysis. Revenue Growth (%) = (Current-year Revenue from Operations − Previous-year Revenue from Operations) ÷ Previous-year Revenue from Operations. FY2024–25 growth uses FY2023–24 comparative revenue, while FY2025–26 growth uses FY2024–25 and FY2025–26 figures from the financial data above. Operating Profit Margin (%) = Operating Profit ÷ Revenue from Operations, where Operating Profit = Revenue from Operations − (Total Expenses − Finance Costs). This measure is calculated consistently across all five companies using their reported figures.
A70: Additional Data - FY2023–24 Revenue from Operations (Reference Only)
A71: This FY2023-24 comparative figure is used only as the denominator for the FY2024-25 Revenue Growth (%) row below; it is not part of the two-year (FY2024-25/FY2025-26) dataset used elsewhere in this sheet. See the sourcing notes at the end of this section.
A72: Line Item - FY2023-24 | C72: Asian Paints
A73: Revenue from Operations | C73: 31226.98
A75: Additional Financial Statement Data (₹ Crore, Standalone) - Inputs for Operating Profit Margin
A76: Line Item | C76: Asian Paints
C77: FY2024-25 | D77: FY2025-26
A78: Total Expenses (Standalone P&L, full total incl. Finance Costs & Depreciation) | C78: 25045.99 | D78: 25802.01
A79: Finance Costs (Standalone) | C79: 143.77 | D79: 127.35
A81: Growth and Profitability Ratios - Formulas, Company Figures & Industry Average
A82: Revenue Growth (%) = (Current-year Revenue − Previous-year Revenue) ÷ Previous-year Revenue. Operating Profit Margin (%) = [Revenue − (Total Expenses − Finance Costs)] ÷ Revenue, i.e. Profit from Operations before Other Income, Finance Costs & Exceptional Items, as a % of Revenue. Industry Avg = simple (arithmetic) average of the same ratio across all five companies selected for this project (same methodology as the rest of this sheet).
C84: FY2024-25 | E84: FY2025-26
A85: Ratio | B85: Formula | C85: Company | D85: Industry Avg | E85: Company | F85: Industry Avg
A86: Revenue Growth (%) | B86: (Current-year Revenue − Previous-year Revenue) ÷ Previous-year Revenue | C86: =(C22-C73)/C73 -> -0.053618057 | D86: ='Industry Summary'!L75 -> 0.0055003858 | E86: =(D22-C22)/C22 -> 0.041174988 | F86: ='Industry Summary'!L80 -> 0.0038760262
A87: Operating Profit Margin (%) | B87: [Revenue − (Total Expenses − Finance Costs)] ÷ Revenue | C87: =(C22-(C78-C79))/C22 -> 0.15736085 | D87: ='Industry Summary'!L76 -> 0.13378096 | E87: =(D22-(D78-D79))/D22 -> 0.16558031 | F87: ='Industry Summary'!L81 -> 0.13140019
A89: G. 3-Factor DuPont Analysis - ROE Decomposition
A90: ROE = Net Profit Margin × Asset Turnover × Equity Multiplier. This decomposition explains ROE through profitability, asset efficiency and financial leverage. Asset Turnover and Equity Multiplier use the same average-balance convention as the ROA and ROE calculations above, ensuring consistent year-wise comparisons for FY2024–25 and FY2025–26.
C92: FY2024-25 | E92: FY2025-26
A93: Component | B93: Formula | C93: Company | D93: Industry Avg | E93: Company | F93: Industry Avg
A94: Net Profit Margin | B94: PAT ÷ Revenue | C94: =C26/C22 -> 0.12130486 | D94: ='Industry Summary'!L51 -> 0.11618978 | E94: =D26/D22 -> 0.13793441 | F94: ='Industry Summary'!L63 -> 0.19305877
A95: Asset Turnover | B95: Revenue ÷ Average Total Assets | C95: =C22/AVERAGE(C37,C21) -> 1.1217822 | D95: ='Industry Summary'!L100 -> 1.1598112 | E95: =D22/AVERAGE(C21,D21) -> 1.0846283 | F95: ='Industry Summary'!L107 -> 1.0467514
A96: Equity Multiplier | B96: Average Total Assets ÷ Average Total Equity | C96: =AVERAGE(C37,C21)/AVERAGE(C36,C20) -> 1.4136229 | D96: ='Industry Summary'!L101 -> 1.530061 | E96: =AVERAGE(C21,D21)/AVERAGE(C20,D20) -> 1.4268154 | F96: ='Industry Summary'!L108 -> 1.4416243
A97: ROE (product) | B97: Net Margin × Asset Turnover × Equity Multiplier | C97: =C94*C95*C96 -> 0.19236245 | D97: =D94*D95*D96 -> 0.20618829 | E97: =E94*E95*E96 -> 0.21346238 | F97: =F94*F95*F96 -> 0.29132998
A98: The Industry Average columns for Net Profit Margin, Asset Turnover and Equity Multiplier are calculated as the simple arithmetic mean of the five companies’ respective ratios, including Asian Paints. Industry Average ROE (product) is the product of these three average components, not the arithmetic mean of the five companies’ ROEs. Therefore, it differs from the direct average ROE: 20.62% versus 20.66% in FY2024–25 and 29.13% versus 33.02% in FY2025–26. The difference is particularly pronounced in FY2025–26 because of JSW Dulux’s exceptional-item-inflated margin. The 5-Factor DuPont analysis below applies the same product-of-averages approach.
A100: H. 5-Factor DuPont Analysis of Return on Equity (Supplementary Analysis, Standalone)
A101: The 5-Factor DuPont model decomposes Return on Equity into five components: Tax Burden, Interest Burden, EBIT Margin, Asset Turnover and Equity Multiplier. Asset Turnover and Equity Multiplier follow the same average-balance convention as the 3-Factor model. The product of all five components reconciles to Net Profit (PAT) ÷ Average Total Equity, the directly calculated ROE. The Reconciliation Difference below verifies this for both financial years.
A103: EBIT is defined here as Profit Before Tax (PBT) + Finance Costs - the standard textbook DuPont definition (“Earnings Before Interest and Tax”), chosen specifically because it makes Interest Burden (PBT ÷ EBIT) a clean, well-behaved ratio and makes the five-factor product reconcile to reported ROE by construction, not by any forced adjustment. Because PBT already includes Other Income and any Exceptional Items, this EBIT (and the EBIT Margin and Interest Burden derived from it) also includes their effect - unlike the “Operating Profit Margin” in the Growth & Profitability Ratios section above, which deliberately excludes Other Income, Finance Costs and Exceptional Items to show recurring operating performance only. The two margins are therefore not the same measure and are not interchangeable: Operating Profit Margin above is the cleaner recurring-operations view; EBIT Margin here is the measure needed for the five-factor ROE decomposition to reconcile exactly.
A105: Factor | B105: Formula | C105: Company | D105: Industry Avg | E105: Company | F105: Industry Avg
A106: Tax Burden | B106: Net Profit (PAT) ÷ Profit Before Tax (PBT) | C106: =C26/C24 -> 0.73202945 | D106: ='Industry Summary'!L116 -> 0.74455076 | E106: =D26/D24 -> 0.74022778 | F106: ='Industry Summary'!L127 -> 0.76399743
A107: Interest Burden | B107: PBT ÷ EBIT (EBIT = PBT + Finance Costs) | C107: =C24/(C24+C79) -> 0.97147958 | D107: ='Industry Summary'!L117 -> 0.97925396 | E107: =D24/(D24+D79) -> 0.97827144 | F107: ='Industry Summary'!L128 -> 0.9817446
A108: EBIT Margin | B108: EBIT ÷ Revenue from Operations | C108: =(C24+C79)/C22 -> 0.17057523 | D108: ='Industry Summary'!L118 -> 0.15948466 | E108: =(D24+D79)/D22 -> 0.19047933 | F108: ='Industry Summary'!L129 -> 0.24689542
A109: Asset Turnover | B109: Revenue ÷ Average Total Assets (as in the 3-Factor DuPont analysis above) | C109: =C95 -> 1.1217822 | D109: ='Industry Summary'!L100 -> 1.1598112 | E109: =E95 -> 1.0846283 | F109: ='Industry Summary'!L107 -> 1.0467514
A110: Equity Multiplier | B110: Average Total Assets ÷ Average Total Equity (as in the 3-Factor DuPont analysis above) | C110: =C96 -> 1.4136229 | D110: ='Industry Summary'!L101 -> 1.530061 | E110: =E96 -> 1.4268154 | F110: ='Industry Summary'!L108 -> 1.4416243
A111: 5-Factor DuPont ROE (product) | B111: Tax Burden × Interest Burden × EBIT Margin × Asset Turnover × Equity Multiplier | C111: =C106*C107*C108*C109*C110 -> 0.19236245 | D111: =D106*D107*D108*D109*D110 -> 0.20635007 | E111: =E106*E107*E108*E109*E110 -> 0.21346238 | F111: =F106*F107*F108*F109*F110 -> 0.27944678
A112: Directly-Calculated ROE (existing, above) | B112: Net Profit (PAT) ÷ Average Total Equity - same figure as the Ratio Analysis / 3-Factor DuPont ROE above | C112: =C60 -> 0.19236245 | D112: =D60 -> 0.20662056 | E112: =E60 -> 0.21346238 | F112: =F60 -> 0.33024035
A113: Reconciliation Difference | B113: 5-Factor DuPont ROE − Directly-Calculated ROE (should be ~0.00%) | C113: =C111-C112 -> 0 | D113: =D111-D112 -> -0.00027049493 | E113: =E111-E112 -> 0 | F113: =F111-F112 -> -0.050793571
A114: The Industry Average in the 5-Factor DuPont ROE row is calculated by multiplying the five separately averaged components: Tax Burden, Interest Burden, EBIT Margin, Asset Turnover and Equity Multiplier. This product of averages differs mathematically from the arithmetic mean of the five companies’ individual ROEs, so the Industry Average Reconciliation Difference is non-zero. This is an averaging-order effect, not a formula error, and is particularly pronounced in FY2025–26 because of JSW Dulux’s exceptional-item-driven results. The individual company columns reconcile to their directly calculated ROE, subject only to rounding.
A116: I. Industry Average Comparisons - Company vs Industry Average (data tables and charts)
A117: Ratio | B117: Company FY24-25 | C117: Industry Avg FY24-25 | D117: Company FY25-26 | E117: Industry Avg FY25-26
A118: Current Ratio | B118: =C45 -> 2.2985007 | C118: =D45 -> 2.4353778 | D118: =E45 -> 2.4631067 | E118: =F45 -> 2.4275972
A119: Quick Ratio | B119: =C46 -> 1.357696 | C119: =D46 -> 1.5808142 | D119: =E46 -> 1.7744366 | E119: =F46 -> 1.6811362
A120: Cash Ratio | B120: =C47 -> 0.032540781 | C120: =D47 -> 0.15262564 | D120: =E47 -> 0.063709341 | E120: =F47 -> 0.11967229
A121: Debt-to-Equity | B121: =C52 -> 0.0020754888 | C121: =D52 -> 0.00042882759 | D121: =E52 -> 0.057246424 | E121: =F52 -> 0.011449285
A122: D/E incl. Lease | B122: =C53 -> 0.063150697 | C122: =D53 -> 0.048453003 | D122: =E53 -> 0.11399337 | E122: =F53 -> 0.053467726
A143: Ratio | B143: Company FY24-25 | C143: Industry Avg FY24-25 | D143: Company FY25-26 | E143: Industry Avg FY25-26
A144: Net Profit Margin | B144: =C58 -> 0.12130486 | C144: =D58 -> 0.11618978 | D144: =E58 -> 0.13793441 | E144: =F58 -> 0.19305877
A145: Return on Assets (ROA) | B145: =C59 -> 0.13607763 | C145: =D59 -> 0.13330559 | D145: =E59 -> 0.14960757 | E145: =F59 -> 0.20609893
A146: Return on Equity (ROE) | B146: =C60 -> 0.19236245 | C146: =D60 -> 0.20662056 | D146: =E60 -> 0.21346238 | E146: =F60 -> 0.33024035
A168: J. Supporting Calculations, Interpretations, Sources and Disclosures
A169: Reporting basis, units and sources - by company (disclosures for the input tables in the Industry Summary sheet)
...

Sheet JSW Dulux
A1: JSW Dulux Ltd. (formerly Akzo Nobel India Ltd.) - Financial Analysis
A2: Standalone Financial Statements | FY2024–25 & FY2025–26 (FY2023–24 Opening Balances) | Amounts in ₹ Crore Unless Stated | Industry Average: Simple Mean of Five Companies
A4: Financial Statement Analysis
A6: A. Key Financial Figures - Financial Statement Data (₹ Crore) - own company inputs used by the analysis
A7: Line Item | C7: JSW Dulux
C8: FY2024-25 | D8: FY2025-26
A9: Inventories (closing stock) | C9: 604.7 | D9: 571.1
A10: Trade Receivables (current) | C10: 584.9 | D10: 602.9
A11: Cash & Cash Equivalents | C11: 247.2 | D11: 203.1
A12: Bank Balances other than Cash & Cash Equivalents | C12: 52.3 | D12: 53.9
A13: Other Current Assets (investments, loans, other financial & non-financial assets) | C13: 511.3 | D13: 289.4
A14: Total Current Assets | C14: 2000.4 | D14: 1720.4
A15: Trade Payables | C15: 956.6 | D15: 753.6
A16: Short-term Borrowings | C16: 0 | D16: 0
A17: Other Current Liabilities & Provisions (incl. current lease liabilities) | C17: 493.6 | D17: 380.7
A18: Total Current Liabilities | C18: 1450.2 | D18: 1134.3
A19: Total Borrowings (interest-bearing debt; excludes lease liabilities) | C19: 0 | D19: 0
A20: Total Equity / Shareholders’ Funds | C20: 1328.7 | D20: 2394.2
... A29: Total Lease Liabilities, Ind AS 116 - excluded from Total Borrowings above (memo) | C29: 62.1 | D29: 79.1
A31: Opening Balances - FY2023–24 Closing (Reference Only)
A32: These three FY2023-24 closing figures come from the comparative column already printed in each company’s FY2024-25 annual report (see citations below) and are used only to compute average-balance ratios for FY2024-25 in the tables below - they are not part of the two-year dataset used in the rest of this analysis.
A34: Line Item - As at 31 March 2024 | C34: JSW Dulux
A35: Inventories (closing stock) | C35: 611.5
A36: Total Equity / Shareholders’ Funds | C36: 1329.2
A37: Total Assets | C37: 2903
A39: Ratio Analysis - Formula, Company Figures & Industry Average
A40: Methodology: Debt-to-Equity excludes Ind AS 116 lease liabilities; a separate lease-inclusive ratio adds Total Lease Liabilities. The Industry Average is the simple arithmetic mean of the same ratio for the five selected companies, including the company being analysed. Supporting financial data is maintained in the Industry Summary sheet, while company-specific ratios are calculated separately for FY2024–25 and FY2025–26. Ratios based on average balances use FY2023–24 closing balances and FY2024–25 closing balances for FY2024–25, and FY2024–25 and FY2025–26 closing balances for FY2025–26. Materials-Consumption Turnover is used as a proxy for Inventory Turnover because a single consolidated Cost of Goods Sold figure is not available for all companies.
A42: B. Liquidity
C43: FY2024-25 | E43: FY2025-26
A44: Ratio | B44: Formula | C44: Company | D44: Industry Avg | E44: Company | F44: Industry Avg
A45: Current Ratio | B45: Current Assets ÷ Current Liabilities | C45: =C14/C18 -> 1.3793959 | D45: ='Industry Summary'!L48 -> 2.4353778 | E45: =D14/D18 -> 1.5167063 | F45: ='Industry Summary'!L60 -> 2.4275972
A46: Quick Ratio | B46: (Current Assets − Inventories) ÷ Current Liabilities | C46: =(C14-C9)/C18 -> 0.96241898 | D46: ='Industry Summary'!L49 -> 1.5808142 | E46: =(D14-D9)/D18 -> 1.013224 | F46: ='Industry Summary'!L61 -> 1.6811362
A47: Cash Ratio | B47: (Cash & Cash Equivalents + Other Bank Balances) ÷ Current Liabilities | C47: =(C11+C12)/C18 -> 0.20652324 | D47: ='Industry Summary'!L50 -> 0.15262564 | E47: =(D11+D12)/D18 -> 0.22657145 | F47: ='Industry Summary'!L62 -> 0.11967229
A49: C. Solvency and Leverage
C50: FY2024-25 | E50: FY2025-26
A51: Ratio | B51: Formula | C51: Company | D51: Industry Avg | E51: Company | F51: Industry Avg
A52: Debt-to-Equity | B52: Total Borrowings ÷ Total Equity | C52: =C19/C20 -> 0 | D52: ='Industry Summary'!L54 -> 0.00042882759 | E52: =D19/D20 -> 0 | F52: ='Industry Summary'!L66 -> 0.011449285
A53: Debt-to-Equity (incl. Lease Liabilities) | B53: (Total Borrowings + Total Lease Liabilities) ÷ Total Equity | C53: =(C19+C29)/C20 -> 0.046737413 | D53: ='Industry Summary'!L55 -> 0.048453003 | E53: =(D19+D29)/D20 -> 0.033038176 | F53: ='Industry Summary'!L67 -> 0.053467726
A55: D. Profitability
C56: FY2024-25 | E56: FY2025-26
A57: Ratio | B57: Formula | C57: Company | D57: Industry Avg | E57: Company | F57: Industry Avg
A58: Net Profit Margin | B58: Net Profit (PAT) ÷ Revenue from Operations | C58: =C26/C22 -> 0.10476144 | D58: ='Industry Summary'!L51 -> 0.11618978 | E58: =D26/D22 -> 0.53281285 | F58: ='Industry Summary'!L63 -> 0.19305877
A59: Return on Assets (ROA) - average basis | B59: Net Profit (PAT) ÷ Average Total Assets (average of prior-year & current-year closing balances, both years) | C59: =C26/AVERAGE(C37,C21) -> 0.14767598 | D59: ='Industry Summary'!L52 -> 0.13330559 | E59: =D26/AVERAGE(C21,D21) -> 0.5784917 | F59: ='Industry Summary'!L64 -> 0.20609893
A60: Return on Equity (ROE) - average basis | B60: Net Profit (PAT) ÷ Average Total Equity (average of prior-year & current-year closing balances, both years) | C60: =C26/AVERAGE(C36,C20) -> 0.32251025 | D60: ='Industry Summary'!L53 -> 0.20662056 | E60: =D26/AVERAGE(C20,D20) -> 1.0302184 | F60: ='Industry Summary'!L65 -> 0.33024035
A62: E. Efficiency and Turnover
C63: FY2024-25 | E63: FY2025-26
A64: Ratio | B64: Formula | C64: Company | D64: Industry Avg | E64: Company | F64: Industry Avg
A65: Materials-Consumption Turnover - average basis | B65: Cost of Materials Consumed ÷ Average Inventories (named explicitly as a proxy - none of the three companies discloses a single consolidated COGS line; average of prior-year & current-year closing inventory, both years) | C65: =C23/AVERAGE(C35,C9) -> 3.5561585 | D65: ='Industry Summary'!L56 -> 3.0528356 | E65: =D23/AVERAGE(C9,D9) -> 3.1777513 | F65: ='Industry Summary'!L68 -> 2.9688388
A67: F. Growth - Growth & Profitability Ratios
A68: This section presents Revenue Growth (%) and Operating Profit Margin (%) for FY2024–25 and FY2025–26, using the same standalone basis and five-company Industry Average methodology as the preceding analysis. Revenue Growth (%) = (Current-year Revenue from Operations − Previous-year Revenue from Operations) ÷ Previous-year Revenue from Operations. FY2024–25 growth uses FY2023–24 comparative revenue, while FY2025–26 growth uses FY2024–25 and FY2025–26 figures from the financial data above. Operating Profit Margin (%) = Operating Profit ÷ Revenue from Operations, where Operating Profit = Revenue from Operations − (Total Expenses − Finance Costs). This measure is calculated consistently across all five companies using their reported figures.
A70: Additional Data - FY2023–24 Revenue from Operations (Reference Only)
A71: This FY2023-24 comparative figure is used only as the denominator for the FY2024-25 Revenue Growth (%) row below; it is not part of the two-year (FY2024-25/FY2025-26) dataset used elsewhere in this sheet. See the sourcing notes at the end of this section.
A72: Line Item - FY2023-24 | C72: JSW Dulux
A73: Revenue from Operations | C73: 3961.6
A75: Additional Financial Statement Data (₹ Crore, Standalone) - Inputs for Operating Profit Margin
A76: Line Item | C76: JSW Dulux
C77: FY2024-25 | D77: FY2025-26
A78: Total Expenses (Standalone P&L, full total incl. Finance Costs & Depreciation) | C78: 3549.1 | D78: 3179.1
A79: Finance Costs (Standalone) | C79: 9.8 | D79: 12.1
A81: Growth and Profitability Ratios - Formulas, Company Figures & Industry Average
A82: Revenue Growth (%) = (Current-year Revenue − Previous-year Revenue) ÷ Previous-year Revenue. Operating Profit Margin (%) = [Revenue − (Total Expenses − Finance Costs)] ÷ Revenue, i.e. Profit from Operations before Other Income, Finance Costs & Exceptional Items, as a % of Revenue. Industry Avg = simple (arithmetic) average of the same ratio across all five companies selected for this project (same methodology as the rest of this sheet).
C84: FY2024-25 | E84: FY2025-26
A85: Ratio | B85: Formula | C85: Company | D85: Industry Avg | E85: Company | F85: Industry Avg
A86: Revenue Growth (%) | B86: (Current-year Revenue − Previous-year Revenue) ÷ Previous-year Revenue | C86: =(C22-C73)/C73 -> 0.032714055 | D86: ='Industry Summary'!L75 -> 0.0055003858 | E86: =(D22-C22)/C22 -> -0.12025811 | F86: ='Industry Summary'!L80 -> 0.0038760262
A87: Operating Profit Margin (%) | B87: [Revenue − (Total Expenses − Finance Costs)] ÷ Revenue | C87: =(C22-(C78-C79))/C22 -> 0.1348993 | D87: ='Industry Summary'!L76 -> 0.13378096 | E87: =(D22-(D78-D79))/D22 -> 0.12008224 | F87: ='Industry Summary'!L81 -> 0.13140019
A89: G. 3-Factor DuPont Analysis - ROE Decomposition
A90: ROE = Net Profit Margin × Asset Turnover × Equity Multiplier. This decomposition explains ROE through profitability, asset efficiency and financial leverage. Asset Turnover and Equity Multiplier use the same average-balance convention as the ROA and ROE calculations above, ensuring consistent year-wise comparisons for FY2024–25 and FY2025–26.
C92: FY2024-25 | E92: FY2025-26
A93: Component | B93: Formula | C93: Company | D93: Industry Avg | E93: Company | F93: Industry Avg
A94: Net Profit Margin | B94: PAT ÷ Revenue | C94: =C26/C22 -> 0.10476144 | D94: ='Industry Summary'!L51 -> 0.11618978 | E94: =D26/D22 -> 0.53281285 | F94: ='Industry Summary'!L63 -> 0.19305877
A95: Asset Turnover | B95: Revenue ÷ Average Total Assets | C95: =C22/AVERAGE(C37,C21) -> 1.4096406 | D95: ='Industry Summary'!L100 -> 1.1598112 | E95: =D22/AVERAGE(C21,D21) -> 1.0857315 | F95: ='Industry Summary'!L107 -> 1.0467514
A96: Equity Multiplier | B96: Average Total Assets ÷ Average Total Equity | C96: =AVERAGE(C37,C21)/AVERAGE(C36,C20) -> 2.1839046 | D96: ='Industry Summary'!L101 -> 1.530061 | E96: =AVERAGE(C21,D21)/AVERAGE(C20,D20) -> 1.7808698 | F96: ='Industry Summary'!L108 -> 1.4416243
A97: ROE (product) | B97: Net Margin × Asset Turnover × Equity Multiplier | C97: =C94*C95*C96 -> 0.32251025 | D97: =D94*D95*D96 -> 0.20618829 | E97: =E94*E95*E96 -> 1.0302184 | F97: =F94*F95*F96 -> 0.29132998
A98: The Industry Average columns for Net Profit Margin, Asset Turnover and Equity Multiplier are calculated as the simple arithmetic mean of the five companies’ respective ratios, including JSW Dulux. Industry Average ROE (product) is the product of these three average components, not the arithmetic mean of the five companies’ ROEs. Therefore, it differs from the direct average ROE: 20.62% versus 20.66% in FY2024–25 and 29.13% versus 33.02% in FY2025–26. The difference is particularly pronounced in FY2025–26 because of JSW Dulux’s exceptional-item-inflated margin. The 5-Factor DuPont analysis below applies the same product-of-averages approach.
A100: H. 5-Factor DuPont Analysis of Return on Equity (Supplementary Analysis, Standalone)
A101: The 5-Factor DuPont model decomposes Return on Equity into five components: Tax Burden, Interest Burden, EBIT Margin, Asset Turnover and Equity Multiplier. Asset Turnover and Equity Multiplier follow the same average-balance convention as the 3-Factor model. The product of all five components reconciles to Net Profit (PAT) ÷ Average Total Equity, the directly calculated ROE. The Reconciliation Difference below verifies this for both financial years.
A103: EBIT is defined here as Profit Before Tax (PBT) + Finance Costs - the standard textbook DuPont definition (“Earnings Before Interest and Tax”), chosen specifically because it makes Interest Burden (PBT ÷ EBIT) a clean, well-behaved ratio and makes the five-factor product reconcile to reported ROE by construction, not by any forced adjustment. Because PBT already includes Other Income and any Exceptional Items, this EBIT (and the EBIT Margin and Interest Burden derived from it) also includes their effect - unlike the “Operating Profit Margin” in the Growth & Profitability Ratios section above, which deliberately excludes Other Income, Finance Costs and Exceptional Items to show recurring operating performance only. The two margins are therefore not the same measure and are not interchangeable: Operating Profit Margin above is the cleaner recurring-operations view; EBIT Margin here is the measure needed for the five-factor ROE decomposition to reconcile exactly.
A105: Factor | B105: Formula | C105: Company | D105: Industry Avg | E105: Company | F105: Industry Avg
A106: Tax Burden | B106: Net Profit (PAT) ÷ Profit Before Tax (PBT) | C106: =C26/C24 -> 0.75232579 | D106: ='Industry Summary'!L116 -> 0.74455076 | E106: =D26/D24 -> 0.83389138 | F106: ='Industry Summary'!L127 -> 0.76399743
A107: Interest Burden | B107: PBT ÷ EBIT (EBIT = PBT + Finance Costs) | C107: =C24/(C24+C79) -> 0.98308887 | D107: ='Industry Summary'!L117 -> 0.97925396 | E107: =D24/(D24+D79) -> 0.99476598 | F107: ='Industry Summary'!L128 -> 0.9817446
A108: EBIT Margin | B108: EBIT ÷ Revenue from Operations | C108: =(C24+C79)/C22 -> 0.14164548 | D108: ='Industry Summary'!L118 -> 0.15948466 | E108: =(D24+D79)/D22 -> 0.6423094 | F108: ='Industry Summary'!L129 -> 0.24689542
A109: Asset Turnover | B109: Revenue ÷ Average Total Assets (as in the 3-Factor DuPont analysis above) | C109: =C95 -> 1.4096406 | D109: ='Industry Summary'!L100 -> 1.1598112 | E109: =E95 -> 1.0857315 | F109: ='Industry Summary'!L107 -> 1.0467514
A110: Equity Multiplier | B110: Average Total Assets ÷ Average Total Equity (as in the 3-Factor DuPont analysis above) | C110: =C96 -> 2.1839046 | D110: ='Industry Summary'!L101 -> 1.530061 | E110: =E96 -> 1.7808698 | F110: ='Industry Summary'!L108 -> 1.4416243
A111: 5-Factor DuPont ROE (product) | B111: Tax Burden × Interest Burden × EBIT Margin × Asset Turnover × Equity Multiplier | C111: =C106*C107*C108*C109*C110 -> 0.32251025 | D111: =D106*D107*D108*D109*D110 -> 0.20635007 | E111: =E106*E107*E108*E109*E110 -> 1.0302184 | F111: =F106*F107*F108*F109*F110 -> 0.27944678
A112: Directly-Calculated ROE (existing, above) | B112: Net Profit (PAT) ÷ Average Total Equity - same figure as the Ratio Analysis / 3-Factor DuPont ROE above | C112: =C60 -> 0.32251025 | D112: =D60 -> 0.20662056 | E112: =E60 -> 1.0302184 | F112: =F60 -> 0.33024035
A113: Reconciliation Difference | B113: 5-Factor DuPont ROE − Directly-Calculated ROE (should be ~0.00%) | C113: =C111-C112 -> 0 | D113: =D111-D112 -> -0.00027049493 | E113: =E111-E112 -> 0 | F113: =F111-F112 -> -0.050793571
A114: The Industry Average in the 5-Factor DuPont ROE row is calculated by multiplying the five separately averaged components: Tax Burden, Interest Burden, EBIT Margin, Asset Turnover and Equity Multiplier. This product of averages differs mathematically from the arithmetic mean of the five companies’ individual ROEs, so the Industry Average Reconciliation Difference is non-zero. This is an averaging-order effect, not a formula error, and is particularly pronounced in FY2025–26 because of JSW Dulux’s exceptional-item-driven results. The individual company columns reconcile to their directly calculated ROE, subject only to rounding.
A116: I. Industry Average Comparisons - Company vs Industry Average (data tables and charts)
A117: Ratio | B117: Company FY24-25 | C117: Industry Avg FY24-25 | D117: Company FY25-26 | E117: Industry Avg FY25-26
A118: Current Ratio | B118: =C45 -> 1.3793959 | C118: =D45 -> 2.4353778 | D118: =E45 -> 1.5167063 | E118: =F45 -> 2.4275972
A119: Quick Ratio | B119: =C46 -> 0.96241898 | C119: =D46 -> 1.5808142 | D119: =E46 -> 1.013224 | E119: =F46 -> 1.6811362
A120: Cash Ratio | B120: =C47 -> 0.20652324 | C120: =D47 -> 0.15262564 | D120: =E47 -> 0.22657145 | E120: =F47 -> 0.11967229
A121: Debt-to-Equity | B121: =C52 -> 0 | C121: =D52 -> 0.00042882759 | D121: =E52 -> 0 | E121: =F52 -> 0.011449285
A122: D/E incl. Lease | B122: =C53 -> 0.046737413 | C122: =D53 -> 0.048453003 | D122: =E53 -> 0.033038176 | E122: =F53 -> 0.053467726
A143: Ratio | B143: Company FY24-25 | C143: Industry Avg FY24-25 | D143: Company FY25-26 | E143: Industry Avg FY25-26
A144: Net Profit Margin | B144: =C58 -> 0.10476144 | C144: =D58 -> 0.11618978 | D144: =E58 -> 0.53281285 | E144: =F58 -> 0.19305877
A145: Return on Assets (ROA) | B145: =C59 -> 0.14767598 | C145: =D59 -> 0.13330559 | D145: =E59 -> 0.5784917 | E145: =F59 -> 0.20609893
A146: Return on Equity (ROE) | B146: =C60 -> 0.32251025 | C146: =D60 -> 0.20662056 | D146: =E60 -> 1.0302184 | E146: =F60 -> 0.33024035
A168: J. Supporting Calculations, Interpretations, Sources and Disclosures
A169: Reporting basis, units and sources - by company (disclosures for the input tables in the Industry Summary sheet)
...

Sheet Indigo Paints
A1: Indigo Paints Ltd. - Financial Analysis
A2: Standalone Financial Statements | FY2024–25 & FY2025–26 (FY2023–24 Opening Balances) | Amounts in ₹ Crore Unless Stated | Industry Average: Simple Mean of Five Companies
A4: Financial Statement Analysis
A6: A. Key Financial Figures - Financial Statement Data (₹ Crore) - own company inputs used by the analysis
A7: Line Item | C7: Indigo Paints
C8: FY2024-25 | D8: FY2025-26
A9: Inventories (closing stock) | C9: 149.13 | D9: 173.07
A10: Trade Receivables (current) | C10: 219.92 | D10: 257.29
A11: Cash & Cash Equivalents | C11: 37.09 | D11: 28.54
A12: Bank Balances other than Cash & Cash Equivalents | C12: 0.01 | D12: 0.01
A13: Other Current Assets (investments, loans, other financial & non-financial assets) | C13: 240.14 | D13: 304.26
A14: Total Current Assets | C14: 646.29 | D14: 763.17
A15: Trade Payables | C15: 165.29 | D15: 199.44
A16: Short-term Borrowings | C16: 0 | D16: 0
A17: Other Current Liabilities & Provisions (incl. current lease liabilities) | C17: 104.19 | D17: 143.48
A18: Total Current Liabilities | C18: 269.48 | D18: 342.92
A19: Total Borrowings (interest-bearing debt; excludes lease liabilities) | C19: 0 | D19: 0
A20: Total Equity / Shareholders’ Funds | C20: 1048.14 | D20: 1182.35
... A29: Total Lease Liabilities, Ind AS 116 - excluded from Total Borrowings above (memo) | C29: 19.7 | D29: 18.38
A31: Opening Balances - FY2023–24 Closing (Reference Only)
A32: These three FY2023-24 closing figures come from the comparative column already printed in each company’s FY2024-25 annual report (see citations below) and are used only to compute average-balance ratios for FY2024-25 in the tables below - they are not part of the two-year dataset used in the rest of this analysis.
A34: Line Item - As at 31 March 2024 | C34: Indigo Paints
A35: Inventories (closing stock) | C35: 166.2
A36: Total Equity / Shareholders’ Funds | C36: 915.07
A37: Total Assets | C37: 1221.95
A39: Ratio Analysis - Formula, Company Figures & Industry Average
A40: Methodology: Debt-to-Equity excludes Ind AS 116 lease liabilities; a separate lease-inclusive ratio adds Total Lease Liabilities. The Industry Average is the simple arithmetic mean of the same ratio for the five selected companies, including the company being analysed. Supporting financial data is maintained in the Industry Summary sheet, while company-specific ratios are calculated separately for FY2024–25 and FY2025–26. Ratios based on average balances use FY2023–24 closing balances and FY2024–25 closing balances for FY2024–25, and FY2024–25 and FY2025–26 closing balances for FY2025–26. Materials-Consumption Turnover is used as a proxy for Inventory Turnover because a single consolidated Cost of Goods Sold figure is not available for all companies.
A42: B. Liquidity
C43: FY2024-25 | E43: FY2025-26
A44: Ratio | B44: Formula | C44: Company | D44: Industry Avg | E44: Company | F44: Industry Avg
A45: Current Ratio | B45: Current Assets ÷ Current Liabilities | C45: =C14/C18 -> 2.3982856 | D45: ='Industry Summary'!L48 -> 2.4353778 | E45: =D14/D18 -> 2.2255045 | F45: ='Industry Summary'!L60 -> 2.4275972
A46: Quick Ratio | B46: (Current Assets − Inventories) ÷ Current Liabilities | C46: =(C14-C9)/C18 -> 1.8448864 | D46: ='Industry Summary'!L49 -> 1.5808142 | E46: =(D14-D9)/D18 -> 1.7208095 | F46: ='Industry Summary'!L61 -> 1.6811362
A47: Cash Ratio | B47: (Cash & Cash Equivalents + Other Bank Balances) ÷ Current Liabilities | C47: =(C11+C12)/C18 -> 0.13767255 | D47: ='Industry Summary'!L50 -> 0.15262564 | E47: =(D11+D12)/D18 -> 0.08325557 | F47: ='Industry Summary'!L62 -> 0.11967229
A49: C. Solvency and Leverage
C50: FY2024-25 | E50: FY2025-26
A51: Ratio | B51: Formula | C51: Company | D51: Industry Avg | E51: Company | F51: Industry Avg
A52: Debt-to-Equity | B52: Total Borrowings ÷ Total Equity | C52: =C19/C20 -> 0 | D52: ='Industry Summary'!L54 -> 0.00042882759 | E52: =D19/D20 -> 0 | F52: ='Industry Summary'!L66 -> 0.011449285
A53: Debt-to-Equity (incl. Lease Liabilities) | B53: (Total Borrowings + Total Lease Liabilities) ÷ Total Equity | C53: =(C19+C29)/C20 -> 0.018795199 | D53: ='Industry Summary'!L55 -> 0.048453003 | E53: =(D19+D29)/D20 -> 0.015545312 | F53: ='Industry Summary'!L67 -> 0.053467726
A55: D. Profitability
C56: FY2024-25 | E56: FY2025-26
A57: Ratio | B57: Formula | C57: Company | D57: Industry Avg | E57: Company | F57: Industry Avg
A58: Net Profit Margin | B58: Net Profit (PAT) ÷ Revenue from Operations | C58: =C26/C22 -> 0.11270054 | D58: ='Industry Summary'!L51 -> 0.11618978 | E58: =D26/D22 -> 0.10930593 | F58: ='Industry Summary'!L63 -> 0.19305877
A59: Return on Assets (ROA) - average basis | B59: Net Profit (PAT) ÷ Average Total Assets (average of prior-year & current-year closing balances, both years) | C59: =C26/AVERAGE(C37,C21) -> 0.11159351 | D59: ='Industry Summary'!L52 -> 0.13330559 | E59: =D26/AVERAGE(C21,D21) -> 0.099320286 | F59: ='Industry Summary'!L64 -> 0.20609893
A60: Return on Equity (ROE) - average basis | B60: Net Profit (PAT) ÷ Average Total Equity (average of prior-year & current-year closing balances, both years) | C60: =C26/AVERAGE(C36,C20) -> 0.14663739 | D60: ='Industry Summary'!L53 -> 0.20662056 | E60: =D26/AVERAGE(C20,D20) -> 0.13036597 | F60: ='Industry Summary'!L65 -> 0.33024035
A62: E. Efficiency and Turnover
C63: FY2024-25 | E63: FY2025-26
A64: Ratio | B64: Formula | C64: Company | D64: Industry Avg | E64: Company | F64: Industry Avg
A65: Materials-Consumption Turnover - average basis | B65: Cost of Materials Consumed ÷ Average Inventories (named explicitly as a proxy - none of the three companies discloses a single consolidated COGS line; average of prior-year & current-year closing inventory, both years) | C65: =C23/AVERAGE(C35,C9) -> 4.1140393 | D65: ='Industry Summary'!L56 -> 3.0528356 | E65: =D23/AVERAGE(C9,D9) -> 4.1104904 | F65: ='Industry Summary'!L68 -> 2.9688388
A67: F. Growth - Growth & Profitability Ratios
A68: This section presents Revenue Growth (%) and Operating Profit Margin (%) for FY2024–25 and FY2025–26, using the same standalone basis and five-company Industry Average methodology as the preceding analysis. Revenue Growth (%) = (Current-year Revenue from Operations − Previous-year Revenue from Operations) ÷ Previous-year Revenue from Operations. FY2024–25 growth uses FY2023–24 comparative revenue, while FY2025–26 growth uses FY2024–25 and FY2025–26 figures from the financial data above. Operating Profit Margin (%) = Operating Profit ÷ Revenue from Operations, where Operating Profit = Revenue from Operations − (Total Expenses − Finance Costs). This measure is calculated consistently across all five companies using their reported figures.
A70: Additional Data - FY2023–24 Revenue from Operations (Reference Only)
A71: This FY2023-24 comparative figure is used only as the denominator for the FY2024-25 Revenue Growth (%) row below; it is not part of the two-year (FY2024-25/FY2025-26) dataset used elsewhere in this sheet. See the sourcing notes at the end of this section.
A72: Line Item - FY2023-24 | C72: Indigo Paints
A73: Revenue from Operations | C73: 1254.86
A75: Additional Financial Statement Data (₹ Crore, Standalone) - Inputs for Operating Profit Margin
A76: Line Item | C76: Indigo Paints
C77: FY2024-25 | D77: FY2025-26
A78: Total Expenses (Standalone P&L, full total incl. Finance Costs & Depreciation) | C78: 1102.42 | D78: 1141.21
A79: Finance Costs (Standalone) | C79: 2.96 | D79: 2.39
A81: Growth and Profitability Ratios - Formulas, Company Figures & Industry Average
A82: Revenue Growth (%) = (Current-year Revenue − Previous-year Revenue) ÷ Previous-year Revenue. Operating Profit Margin (%) = [Revenue − (Total Expenses − Finance Costs)] ÷ Revenue, i.e. Profit from Operations before Other Income, Finance Costs & Exceptional Items, as a % of Revenue. Industry Avg = simple (arithmetic) average of the same ratio across all five companies selected for this project (same methodology as the rest of this sheet).
C84: FY2024-25 | E84: FY2025-26
A85: Ratio | B85: Formula | C85: Company | D85: Industry Avg | E85: Company | F85: Industry Avg
A86: Revenue Growth (%) | B86: (Current-year Revenue − Previous-year Revenue) ÷ Previous-year Revenue | C86: =(C22-C73)/C73 -> 0.017794814 | D86: ='Industry Summary'!L75 -> 0.0055003858 | E86: =(D22-C22)/C22 -> 0.041442542 | F86: ='Industry Summary'!L80 -> 0.0038760262
A87: Operating Profit Margin (%) | B87: [Revenue − (Total Expenses − Finance Costs)] ÷ Revenue | C87: =(C22-(C78-C79))/C22 -> 0.13915706 | D87: ='Industry Summary'!L76 -> 0.13378096 | E87: =(D22-(D78-D79))/D22 -> 0.14382161 | F87: ='Industry Summary'!L81 -> 0.13140019
A89: G. 3-Factor DuPont Analysis - ROE Decomposition
A90: ROE = Net Profit Margin × Asset Turnover × Equity Multiplier. This decomposition explains ROE through profitability, asset efficiency and financial leverage. Asset Turnover and Equity Multiplier use the same average-balance convention as the ROA and ROE calculations above, ensuring consistent year-wise comparisons for FY2024–25 and FY2025–26.
C92: FY2024-25 | E92: FY2025-26
A93: Component | B93: Formula | C93: Company | D93: Industry Avg | E93: Company | F93: Industry Avg
A94: Net Profit Margin | B94: PAT ÷ Revenue | C94: =C26/C22 -> 0.11270054 | D94: ='Industry Summary'!L51 -> 0.11618978 | E94: =D26/D22 -> 0.10930593 | F94: ='Industry Summary'!L63 -> 0.19305877
A95: Asset Turnover | B95: Revenue ÷ Average Total Assets | C95: =C22/AVERAGE(C37,C21) -> 0.99017723 | D95: ='Industry Summary'!L100 -> 1.1598112 | E95: =D22/AVERAGE(C21,D21) -> 0.90864501 | F95: ='Industry Summary'!L107 -> 1.0467514
A96: Equity Multiplier | B96: Average Total Assets ÷ Average Total Equity | C96: =AVERAGE(C37,C21)/AVERAGE(C36,C20) -> 1.3140316 | D96: ='Industry Summary'!L101 -> 1.530061 | E96: =AVERAGE(C21,D21)/AVERAGE(C20,D20) -> 1.3125815 | F96: ='Industry Summary'!L108 -> 1.4416243
A97: ROE (product) | B97: Net Margin × Asset Turnover × Equity Multiplier | C97: =C94*C95*C96 -> 0.14663739 | D97: =D94*D95*D96 -> 0.20618829 | E97: =E94*E95*E96 -> 0.13036597 | F97: =F94*F95*F96 -> 0.29132998
A98: The Industry Average columns for Net Profit Margin, Asset Turnover and Equity Multiplier are calculated as the simple arithmetic mean of the five companies’ respective ratios, including Indigo Paints. Industry Average ROE (product) is the product of these three average components, not the arithmetic mean of the five companies’ ROEs. Therefore, it differs from the direct average ROE: 20.62% versus 20.66% in FY2024–25 and 29.13% versus 33.02% in FY2025–26. The difference is particularly pronounced in FY2025–26 because of JSW Dulux’s exceptional-item-inflated margin. The 5-Factor DuPont analysis below applies the same product-of-averages approach.
A100: H. 5-Factor DuPont Analysis of Return on Equity (Supplementary Analysis, Standalone)
A101: The 5-Factor DuPont model decomposes Return on Equity into five components: Tax Burden, Interest Burden, EBIT Margin, Asset Turnover and Equity Multiplier. Asset Turnover and Equity Multiplier follow the same average-balance convention as the 3-Factor model. The product of all five components reconciles to Net Profit (PAT) ÷ Average Total Equity, the directly calculated ROE. The Reconciliation Difference below verifies this for both financial years.
A103: EBIT is defined here as Profit Before Tax (PBT) + Finance Costs - the standard textbook DuPont definition (“Earnings Before Interest and Tax”), chosen specifically because it makes Interest Burden (PBT ÷ EBIT) a clean, well-behaved ratio and makes the five-factor product reconcile to reported ROE by construction, not by any forced adjustment. Because PBT already includes Other Income and any Exceptional Items, this EBIT (and the EBIT Margin and Interest Burden derived from it) also includes their effect - unlike the “Operating Profit Margin” in the Growth & Profitability Ratios section above, which deliberately excludes Other Income, Finance Costs and Exceptional Items to show recurring operating performance only. The two margins are therefore not the same measure and are not interchangeable: Operating Profit Margin above is the cleaner recurring-operations view; EBIT Margin here is the measure needed for the five-factor ROE decomposition to reconcile exactly.
A105: Factor | B105: Formula | C105: Company | D105: Industry Avg | E105: Company | F105: Industry Avg
A106: Tax Burden | B106: Net Profit (PAT) ÷ Profit Before Tax (PBT) | C106: =C26/C24 -> 0.74879051 | D106: ='Industry Summary'!L116 -> 0.74455076 | E106: =D26/D24 -> 0.74455882 | F106: ='Industry Summary'!L127 -> 0.76399743
A107: Interest Burden | B107: PBT ÷ EBIT (EBIT = PBT + Finance Costs) | C107: =C24/(C24+C79) -> 0.98483529 | D107: ='Industry Summary'!L117 -> 0.97925396 | E107: =D24/(D24+D79) -> 0.98790853 | F107: ='Industry Summary'!L128 -> 0.9817446
A108: EBIT Margin | B108: EBIT ÷ Revenue from Operations | C108: =(C24+C79)/C22 -> 0.15282769 | D108: ='Industry Summary'!L118 -> 0.15948466 | E108: =(D24+D79)/D22 -> 0.14860313 | F108: ='Industry Summary'!L129 -> 0.24689542
A109: Asset Turnover | B109: Revenue ÷ Average Total Assets (as in the 3-Factor DuPont analysis above) | C109: =C95 -> 0.99017723 | D109: ='Industry Summary'!L100 -> 1.1598112 | E109: =E95 -> 0.90864501 | F109: ='Industry Summary'!L107 -> 1.0467514
A110: Equity Multiplier | B110: Average Total Assets ÷ Average Total Equity (as in the 3-Factor DuPont analysis above) | C110: =C96 -> 1.3140316 | D110: ='Industry Summary'!L101 -> 1.530061 | E110: =E96 -> 1.3125815 | F110: ='Industry Summary'!L108 -> 1.4416243
A111: 5-Factor DuPont ROE (product) | B111: Tax Burden × Interest Burden × EBIT Margin × Asset Turnover × Equity Multiplier | C111: =C106*C107*C108*C109*C110 -> 0.14663739 | D111: =D106*D107*D108*D109*D110 -> 0.20635007 | E111: =E106*E107*E108*E109*E110 -> 0.13036597 | F111: =F106*F107*F108*F109*F110 -> 0.27944678
A112: Directly-Calculated ROE (existing, above) | B112: Net Profit (PAT) ÷ Average Total Equity - same figure as the Ratio Analysis / 3-Factor DuPont ROE above | C112: =C60 -> 0.14663739 | D112: =D60 -> 0.20662056 | E112: =E60 -> 0.13036597 | F112: =F60 -> 0.33024035
A113: Reconciliation Difference | B113: 5-Factor DuPont ROE − Directly-Calculated ROE (should be ~0.00%) | C113: =C111-C112 -> 0 | D113: =D111-D112 -> -0.00027049493 | E113: =E111-E112 -> 0 | F113: =F111-F112 -> -0.050793571
A114: The Industry Average in the 5-Factor DuPont ROE row is calculated by multiplying the five separately averaged components: Tax Burden, Interest Burden, EBIT Margin, Asset Turnover and Equity Multiplier. This product of averages differs mathematically from the arithmetic mean of the five companies’ individual ROEs, so the Industry Average Reconciliation Difference is non-zero. This is an averaging-order effect, not a formula error, and is particularly pronounced in FY2025–26 because of JSW Dulux’s exceptional-item-driven results. The individual company columns reconcile to their directly calculated ROE, subject only to rounding.
A116: I. Industry Average Comparisons - Company vs Industry Average (data tables and charts)
A117: Ratio | B117: Company FY24-25 | C117: Industry Avg FY24-25 | D117: Company FY25-26 | E117: Industry Avg FY25-26
A118: Current Ratio | B118: =C45 -> 2.3982856 | C118: =D45 -> 2.4353778 | D118: =E45 -> 2.2255045 | E118: =F45 -> 2.4275972
A119: Quick Ratio | B119: =C46 -> 1.8448864 | C119: =D46 -> 1.5808142 | D119: =E46 -> 1.7208095 | E119: =F46 -> 1.6811362
A120: Cash Ratio | B120: =C47 -> 0.13767255 | C120: =D47 -> 0.15262564 | D120: =E47 -> 0.08325557 | E120: =F47 -> 0.11967229
A121: Debt-to-Equity | B121: =C52 -> 0 | C121: =D52 -> 0.00042882759 | D121: =E52 -> 0 | E121: =F52 -> 0.011449285
A122: D/E incl. Lease | B122: =C53 -> 0.018795199 | C122: =D53 -> 0.048453003 | D122: =E53 -> 0.015545312 | E122: =F53 -> 0.053467726
A143: Ratio | B143: Company FY24-25 | C143: Industry Avg FY24-25 | D143: Company FY25-26 | E143: Industry Avg FY25-26
A144: Net Profit Margin | B144: =C58 -> 0.11270054 | C144: =D58 -> 0.11618978 | D144: =E58 -> 0.10930593 | E144: =F58 -> 0.19305877
A145: Return on Assets (ROA) | B145: =C59 -> 0.11159351 | C145: =D59 -> 0.13330559 | D145: =E59 -> 0.099320286 | E145: =F59 -> 0.20609893
A146: Return on Equity (ROE) | B146: =C60 -> 0.14663739 | C146: =D60 -> 0.20662056 | D146: =E60 -> 0.13036597 | E146: =F60 -> 0.33024035
A168: J. Supporting Calculations, Interpretations, Sources and Disclosures
A169: Reporting basis, units and sources - by company (disclosures for the input tables in the Industry Summary sheet)
...

Sheet Industry Summary
A1: Paints & Coatings Industry - Combined Industry Summary
A2: Berger Paints | Kansai Nerolac | Asian Paints | Indigo Paints | JSW Dulux (formerly Akzo Nobel India) - FY2021-22 to FY2025-26
A3: Ratios, DuPont components and Industry Averages on this sheet are live Excel formulas calculated on this sheet from the “Five-Company Financial Data - Local Calculation Support” tables in section 1 at the top of the sheet; no formula refers to any company worksheet, so this sheet calculates independently. Company-profile, market-capitalisation, share-price and Leaders & Laggards items are static copies of the verified values on each company sheet (see each company sheet's Sources & page citations for the primary-source evidence). Unavailable or non-comparable figures are labelled "n/a" or "not separately verified" rather than estimated.
A6: 1. Five-Company Financial Data - Local Calculation Support
A7: Self-contained sheet: the five tables below (side by side) hold the validated standalone book values (₹ Crore) for FY2024-25 and FY2025-26 plus FY2023-24 opening / base figures. Blue = input. Every ratio, DuPont component and Industry Average on this sheet is a live formula calculated from these tables; no formula refers to any company worksheet. Scroll right for all five tables (column A stays in view).
A9: Five-company book values (₹ Crore, Standalone) - Berger Paints | Asian Paints | Indigo Paints | JSW Dulux | Kansai Nerolac - one table per company, side by side
A10: Line item (₹ Crore) | B10: Berger Paints India Ltd. | F10: Asian Paints Ltd. | J10: Indigo Paints Ltd. | N10: JSW Dulux Ltd. (formerly Akzo Nobel India Ltd.) | R10: Kansai Nerolac Paints Ltd.
B11: FY2024-25 | D11: FY2025-26 | F11: FY2024-25 | H11: FY2025-26 | J11: FY2024-25 | L11: FY2025-26 | N11: FY2024-25 | P11: FY2025-26 | R11: FY2024-25 | T11: FY2025-26
A12: Reporting basis (full notes in section J) | B12: ₹ Crore as reported (standalone) | F12: ₹ Crore; FY2024-25 as originally published (restated in FY2025-26 report) | J12: Reported in ₹ lakh; converted to ₹ Crore (÷100) | N12: Reported in ₹ million; converted to ₹ Crore (÷10); FY2024-25 revenue regrouped | R12: ₹ Crore as reported; exceptional items in both years
A13: Inventories (closing stock) | B13: 2206.6 | D13: 2225.6 | F13: 5848.23 | H13: 4824.74 | J13: 149.13 | L13: 173.07 | N13: 604.7 | P13: 571.1 | R13: 1609.71 | T13: 1492.92
A14: Trade Receivables (current) | B14: 1124.37 | D14: 1129.27 | F14: 3197.55 | H14: 3227.71 | J14: 219.92 | L14: 257.29 | N14: 584.9 | P14: 602.9 | R14: 1274.7 | T14: 1379.83
A15: Cash & Cash Equivalents | B15: 141.39 | D15: 151.94 | F15: 176.19 | H15: 395.38 | J15: 37.09 | L15: 28.54 | N15: 247.2 | P15: 203.1 | R15: 85.72 | T15: 184.12
A16: Bank Balances other than Cash & Cash Equivalents | B16: 224.46 | D16: 55.01 | F16: 26.09 | H16: 50.96 | J16: 0.01 | L16: 0.01 | N16: 52.3 | P16: 53.9 | R16: 174.52 | T16: 7.97
A17: Other Current Assets (investments, loans, other) | B17: 436.98 | D17: 1118.69 | F17: 5039.88 | H17: 8757.44 | J17: 240.14 | L17: 304.26 | N17: 511.3 | P17: 289.4 | R17: 2029.11 | T17: 2549.88
A18: Total Current Assets | B18: 4133.8 | D18: 4680.51 | F18: 14287.94 | H18: 17256.23 | J18: 646.29 | L18: 763.17 | N18: 2000.4 | P18: 1720.4 | R18: 5173.76 | T18: 5614.72
A19: Trade Payables | B19: 1569.34 | D19: 1522.26 | F19: 3123.69 | H19: 3114.48 | J19: 165.29 | L19: 199.44 | N19: 956.6 | P19: 753.6 | R19: 1023.65 | T19: 1075.42
A20: Short-term Borrowings | B20: 0.39 | D20: 0 | F20: 2.15 | H20: 340.73 | J20: 0 | L20: 0 | N20: 0 | P20: 0 | R20: 0 | T20: 0
A21: Other Current Liabilities & Provisions | B21: 416.03 | D21: 619.85 | F21: 3090.36 | H21: 3550.67 | J21: 104.19 | L21: 143.48 | N21: 493.6 | P21: 380.7 | R21: 263.68 | T21: 422.77
A22: Total Current Liabilities | B22: 1985.76 | D22: 2142.11 | F22: 6216.2 | H22: 7005.88 | J22: 269.48 | L22: 342.92 | N22: 1450.2 | P22: 1134.3 | R22: 1287.33 | T22: 1498.19
A23: Total Borrowings (excl. lease liabilities) | B23: 0.39 | D23: 0 | F23: 39.4 | H23: 1189.67 | J23: 0 | L23: 0 | N23: 0 | P23: 0 | R23: 0 | T23: 0
A24: Total Equity / Shareholders’ Funds | B24: 5681.06 | D24: 6342.9 | F24: 18983.48 | H24: 20781.56 | J24: 1048.14 | L24: 1182.35 | N24: 1328.7 | P24: 2394.2 | R24: 6366.23 | T24: 6695.77
... A35: Finance Costs (Standalone) | B35: 47.86 | D35: 45.6 | F35: 143.77 | H35: 127.35 | J35: 2.96 | L35: 2.39 | N35: 9.8 | P35: 12.1 | R35: 15.09 | T35: 18.41
A36: Opening balances - FY2023-24 closing (as at 31 March 2024) | B36: FY2023-24 | F36: FY2023-24 | J36: FY2023-24 | N36: FY2023-24 | R36: FY2023-24
A37: Inventories (closing stock) | B37: 2019.43 | F37: 5155.59 | J37: 166.2 | N37: 611.5 | R37: 1616.04
A38: Total Equity / Shareholders’ Funds | B38: 5005.24 | F38: 18288.66 | J38: 915.07 | N38: 1329.2 | R38: 5653.12
A39: Total Assets | B39: 7581.66 | F39: 26035.64 | J39: 1221.95 | N39: 2903 | R39: 7224.8
A40: Revenue from Operations (growth base year) | B40: 10002.93 | F40: 31226.98 | J40: 1254.86 | N40: 3961.6 | R40: 7393.3
A42: Reporting-basis notes: Asian Paints - FY2024-25 figures as originally published (the FY2025-26 report restates comparatives for an amalgamation, differences about 0.1% or less); Revenue, Trade Payables and Total Expenses are sums of reported lines. Indigo Paints - converted from ₹ lakh (÷100); Cost of Materials Consumed is the P&L line “Cost of raw materials and components consumed”. JSW Dulux - converted from ₹ million (÷10); FY2024-25 Revenue ₹4,091.2 Cr and Total Expenses ₹3,549.1 Cr as originally published (FY2025-26 report regrouped promotional spends: ₹4,069.3 Cr / ₹3,527.2 Cr; profit unchanged); FY2025-26 profit before tax includes a ₹1,846.3 Cr net exceptional gain (mainly the profit on the slump sale of two divisions). Berger Paints and Kansai Nerolac - as reported. Trade Payables for Berger, Indigo, JSW and Asian Paints are the sum of the MSME and other-creditor lines. See each company's own worksheet for full source citations.
A43: 2. Financial Ratios - Company Figures, FY2024-25 & FY2025-26
A44: Formula definitions and average-balance methodology are documented on each company's own “Ratio Analysis” table. Columns B–F show each company's own (“Company”) figures; column G, “Industry Avg (5 companies)”, is the simple arithmetic mean of those five company figures for the same year (a live formula); the company figures themselves are calculated on this sheet from the local book-value tables in section 1 at the top of the sheet - a benchmark of the five companies selected for this project, not an official industry-wide average.
A46: FY2024-25
B47: Berger Paints | D47: Asian Paints | F47: Indigo Paints | H47: JSW Dulux (fmrly Akzo Nobel India) | J47: Kansai Nerolac | L47: Industry Avg (5 companies)
A48: Current Ratio | B48: =B18/B22 -> 2.0817219 | D48: =F18/F22 -> 2.2985007 | F48: =J18/J22 -> 2.3982856 | H48: =N18/N22 -> 1.3793959 | J48: =R18/R22 -> 4.018985 | L48: =AVERAGE(B48:J48) -> 2.4353778
A49: Quick Ratio | B49: =(B18-B13)/B22 -> 0.97051003 | D49: =(F18-F13)/F22 -> 1.357696 | F49: =(J18-J13)/J22 -> 1.8448864 | H49: =(N18-N13)/N22 -> 0.96241898 | J49: =(R18-R13)/R22 -> 2.7685597 | L49: =AVERAGE(B49:J49) -> 1.5808142
A50: Cash Ratio | B50: =(B15+B16)/B22 -> 0.18423677 | D50: =(F15+F16)/F22 -> 0.032540781 | F50: =(J15+J16)/J22 -> 0.13767255 | H50: =(N15+N16)/N22 -> 0.20652324 | J50: =(R15+R16)/R22 -> 0.20215485 | L50: =AVERAGE(B50:J50) -> 0.15262564
A51: Net Profit Margin | B51: =B30/B26 -> 0.105957 | D51: =F30/F26 -> 0.12130486 | F51: =J30/J26 -> 0.11270054 | H51: =N30/N26 -> 0.10476144 | J51: =R30/R26 -> 0.13622509 | L51: =AVERAGE(B51:J51) -> 0.11618978
A52: Return on Assets (ROA) - avg. basis | B52: =B30/AVERAGE(B39,B25) -> 0.13675446 | D52: =F30/AVERAGE(F39,F25) -> 0.13607763 | F52: =J30/AVERAGE(J39,J25) -> 0.11159351 | H52: =N30/AVERAGE(N39,N25) -> 0.14767598 | J52: =R30/AVERAGE(R39,R25) -> 0.13442639 | L52: =AVERAGE(B52:J52) -> 0.13330559
A53: Return on Equity (ROE) - avg. basis | B53: =B30/AVERAGE(B38,B24) -> 0.20166007 | D53: =F30/AVERAGE(F38,F24) -> 0.19236245 | F53: =J30/AVERAGE(J38,J24) -> 0.14663739 | H53: =N30/AVERAGE(N38,N24) -> 0.32251025 | J53: =R30/AVERAGE(R38,R24) -> 0.16993265 | L53: =AVERAGE(B53:J53) -> 0.20662056
A54: Debt-to-Equity | B54: =B23/B24 -> 6.8649161e-05 | D54: =F23/F24 -> 0.0020754888 | F54: =J23/J24 -> 0 | H54: =N23/N24 -> 0 | J54: =R23/R24 -> 0 | L54: =AVERAGE(B54:J54) -> 0.00042882759
A55: Debt-to-Equity (incl. Lease Liab.) | B55: =(B23+B33)/B24 -> 0.086689808 | D55: =(F23+F33)/F24 -> 0.063150697 | F55: =(J23+J33)/J24 -> 0.018795199 | H55: =(N23+N33)/N24 -> 0.046737413 | J55: =(R23+R33)/R24 -> 0.026891897 | L55: =AVERAGE(B55:J55) -> 0.048453003
A56: Materials-Consumption Turnover - avg. basis | B56: =B27/AVERAGE(B37,B13) -> 2.4859218 | D56: =F27/AVERAGE(F37,F13) -> 2.4061317 | F56: =J27/AVERAGE(J37,J13) -> 4.1140393 | H56: =N27/AVERAGE(N37,N13) -> 3.5561585 | J56: =R27/AVERAGE(R37,R13) -> 2.7019267 | L56: =AVERAGE(B56:J56) -> 3.0528356
A58: FY2025-26
B59: Berger Paints | D59: Asian Paints | F59: Indigo Paints | H59: JSW Dulux (fmrly Akzo Nobel India) | J59: Kansai Nerolac | L59: Industry Avg (5 companies)
A60: Current Ratio | B60: =D18/D22 -> 2.1849998 | D60: =H18/H22 -> 2.4631067 | F60: =L18/L22 -> 2.2255045 | H60: =P18/P22 -> 1.5167063 | J60: =T18/T22 -> 3.7476689 | L60: =AVERAGE(B60:J60) -> 2.4275972
A61: Quick Ratio | B61: =(D18-D13)/D22 -> 1.1460242 | D61: =(H18-H13)/H22 -> 1.7744366 | F61: =(L18-L13)/L22 -> 1.7208095 | H61: =(P18-P13)/P22 -> 1.013224 | J61: =(T18-T13)/T22 -> 2.7511864 | L61: =AVERAGE(B61:J61) -> 1.6811362
A62: Cash Ratio | B62: =(D15+D16)/D22 -> 0.096610351 | D62: =(H15+H16)/H22 -> 0.063709341 | F62: =(L15+L16)/L22 -> 0.08325557 | H62: =(P15+P16)/P22 -> 0.22657145 | J62: =(T15+T16)/T22 -> 0.12821471 | L62: =AVERAGE(B62:J62) -> 0.11967229
A63: Net Profit Margin | B63: =D30/D26 -> 0.1051487 | D63: =H30/H26 -> 0.13793441 | F63: =L30/L26 -> 0.10930593 | H63: =P30/P26 -> 0.53281285 | J63: =T30/T26 -> 0.080091947 | L63: =AVERAGE(B63:J63) -> 0.19305877
A64: Return on Assets (ROA) - avg. basis | B64: =D30/AVERAGE(B25,D25) -> 0.12797741 | D64: =H30/AVERAGE(F25,H25) -> 0.14960757 | F64: =L30/AVERAGE(J25,L25) -> 0.099320286 | H64: =P30/AVERAGE(N25,P25) -> 0.5784917 | J64: =T30/AVERAGE(R25,T25) -> 0.075097696 | L64: =AVERAGE(B64:J64) -> 0.20609893
A65: Return on Equity (ROE) - avg. basis | B65: =D30/AVERAGE(B24,D24) -> 0.18224612 | D65: =H30/AVERAGE(F24,H24) -> 0.21346238 | F65: =L30/AVERAGE(J24,L24) -> 0.13036597 | H65: =P30/AVERAGE(N24,P24) -> 1.0302184 | J65: =T30/AVERAGE(R24,T24) -> 0.094908896 | L65: =AVERAGE(B65:J65) -> 0.33024035
A66: Debt-to-Equity | B66: =D23/D24 -> 0 | D66: =H23/H24 -> 0.057246424 | F66: =L23/L24 -> 0 | H66: =P23/P24 -> 0 | J66: =T23/T24 -> 0 | L66: =AVERAGE(B66:J66) -> 0.011449285
A67: Debt-to-Equity (incl. Lease Liab.) | B67: =(D23+D33)/D24 -> 0.072323385 | D67: =(H23+H33)/H24 -> 0.11399337 | F67: =(L23+L33)/L24 -> 0.015545312 | H67: =(P23+P33)/P24 -> 0.033038176 | J67: =(T23+T33)/T24 -> 0.03243839 | L67: =AVERAGE(B67:J67) -> 0.053467726
A68: Materials-Consumption Turnover - avg. basis | B68: =D27/AVERAGE(B13,D13) -> 2.3567529 | D68: =H27/AVERAGE(F13,H13) -> 2.37437 | F68: =L27/AVERAGE(J13,L13) -> 4.1104904 | H68: =P27/AVERAGE(N13,P13) -> 3.1777513 | J68: =T27/AVERAGE(R13,T13) -> 2.8248293 | L68: =AVERAGE(B68:J68) -> 2.9688388
A70: 3. Growth & Profitability Ratios - Revenue Growth (%) and Operating Profit Margin (%)
A71: Revenue Growth (%) and Operating Profit Margin (%) are added here as live formulas calculated on this sheet from the local book-value tables in section 1 at the top of the sheet (the same definitions as each company's own "Growth & Profitability Ratios" sub-table - see that sheet for the data sources and methodology note). Operating Profit = Revenue from Operations − (Total Expenses − Finance Costs), i.e. Profit from Operations before Other Income, Finance Costs & Exceptional Items; it deliberately excludes the one-off exceptional items discussed in Section 10 below (most notably JSW Dulux's FY2025-26 slump-sale exceptional gain), unlike Net Profit Margin. Column G, “Industry Avg (5 companies)”, is the arithmetic mean of the five company figures for the year.
A73: FY2024-25
B74: Berger Paints | D74: Asian Paints | F74: Indigo Paints | H74: JSW Dulux (fmrly Akzo Nobel India) | J74: Kansai Nerolac | L74: Industry Avg (5 companies)
A75: Revenue Growth (%) | B75: =(B26-B40)/B40 -> 0.016624129 | D75: =(F26-F40)/F40 -> -0.053618057 | F75: =(J26-J40)/J40 -> 0.017794814 | H75: =(N26-N40)/N40 -> 0.032714055 | J75: =(R26-R40)/R40 -> 0.013986988 | L75: =AVERAGE(B75:J75) -> 0.0055003858
A76: Operating Profit Margin (%) | B76: =(B26-(B34-B35))/B26 -> 0.13338191 | D76: =(F26-(F34-F35))/F26 -> 0.15736085 | F76: =(J26-(J34-J35))/J26 -> 0.13915706 | H76: =(N26-(N34-N35))/N26 -> 0.1348993 | J76: =(R26-(R34-R35))/R26 -> 0.10410567 | L76: =AVERAGE(B76:J76) -> 0.13378096
A78: FY2025-26
B79: Berger Paints | D79: Asian Paints | F79: Indigo Paints | H79: JSW Dulux (fmrly Akzo Nobel India) | J79: Kansai Nerolac | L79: Industry Avg (5 companies)
A80: Revenue Growth (%) | B80: =(D26-B26)/B26 -> 0.024670525 | D80: =(H26-F26)/F26 -> 0.041174988 | F80: =(L26-J26)/J26 -> 0.041442542 | H80: =(P26-N26)/N26 -> -0.12025811 | J80: =(T26-R26)/R26 -> 0.032350191 | L80: =AVERAGE(B80:J80) -> 0.0038760262
A81: Operating Profit Margin (%) | B81: =(D26-(D34-D35))/D26 -> 0.12868782 | D81: =(H26-(H34-H35))/H26 -> 0.16558031 | F81: =(L26-(L34-L35))/L26 -> 0.14382161 | H81: =(P26-(P34-P35))/P26 -> 0.12008224 | J81: =(T26-(T34-T35))/T26 -> 0.098828953 | L81: =AVERAGE(B81:J81) -> 0.13140019
A83: Growth & Profitability - Cross-Company Interpretation
A84: • Revenue growth: in each year four of the five companies grew. The exceptions were Asian Paints in FY2024-25 (-5.36%, then +4.12%) and JSW Dulux in FY2025-26 (-12.03%, after +3.27%). • Operating profit margin leaves out other income, finance costs and exceptional items, so it shows core operating performance. • Asian Paints has the highest operating profit margin in both years (15.74% and 16.56%), even though its revenue fell in FY2024-25. • Indigo Paints (13.92% to 14.38%) and Asian Paints improved their margins. Berger (13.34% to 12.87%), Kansai Nerolac (10.41% to 9.88%) and JSW Dulux (13.49% to 12.01%) saw margins fall. • Berger and Kansai Nerolac grew revenue in both years but their margins still fell, so growth did not give better profitability for them. • JSW Dulux shows why this margin is useful. Its net profit margin jumped (10.48% to 53.28%) because of a one-off gain, but its operating margin fell. • These are only observed patterns. No cause is proven.
A87: 4. Five-Company Industry-Average Methodology
A88: Every “Industry Avg” figure in this workbook - column G of the ratio tables on this sheet and the Industry Avg columns on each company's own Ratio Analysis, DuPont, Growth & Profitability and 5-Factor DuPont tables - is calculated as Industry Average = (Berger Paints + Asian Paints + Indigo Paints + JSW Dulux + Kansai Nerolac) ÷ 5, using the corresponding ratio for the same financial year, separately for FY2024-25 and FY2025-26. Each company worksheet calculates its own Industry Avg cells with live AVERAGE formulas over the five companies' ratios, each calculated locally from the five-company book values held on that worksheet; this Industry Summary does the same from its own local book-value tables (column G averages columns B–F). No worksheet depends on any other, and because all use the same validated inputs and definitions the figures agree. All five companies are always included, so every company sheet shows the same Industry Avg figure and each company is part of its own benchmark. This is the arithmetic average of the five companies selected for this project; it is NOT an official published industry-wide average and is not a ratio computed from aggregated financial statements. Because it is a simple (unweighted) average of only five companies, one outlier moves it noticeably - most notably JSW Dulux's FY2025-26 figures, which are inflated by a one-off exceptional gain (mainly the profit on the slump sale of two divisions) (see Section 10) and lift the FY2025-26 averages for Net Profit Margin, ROA, ROE and EBIT Margin well above any recurring level. For the DuPont analyses (three-factor and five-factor), each factor is averaged across the five companies first and the averaged factors are then multiplied; that product does not in general equal the average of the five companies' ROEs, and the resulting reconciliation differences are shown, not forced to zero.
A94: 5. DuPont Analysis - ROE Decomposition, FY2024-25 & FY2025-26
A95: ROE = Net Profit Margin × Asset Turnover × Equity Multiplier. Re-verified to reconcile exactly (to ≥10 decimal places) against each company's directly-computed ROE for both years - see the accompanying workbook's own audit trail. Column G (“Industry Avg (5 companies)”) averages each component across the five companies; its ROE (product) cell multiplies the three averaged components, so it differs from the average of the five companies' own ROEs shown in the Ratio Analysis table above (20.62% against 20.66% in FY2024-25; 29.13% against 33.02% in FY2025-26).
A97: FY2024-25
B98: Berger Paints | D98: Asian Paints | F98: Indigo Paints | H98: JSW Dulux (fmrly Akzo Nobel India) | J98: Kansai Nerolac | L98: Industry Avg (5 companies)
A99: Net Profit Margin | B99: =B30/B26 -> 0.105957 | D99: =F30/F26 -> 0.12130486 | F99: =J30/J26 -> 0.11270054 | H99: =N30/N26 -> 0.10476144 | J99: =R30/R26 -> 0.13622509 | L99: =AVERAGE(B99:J99) -> 0.11618978
A100: Asset Turnover | B100: =B26/AVERAGE(B39,B25) -> 1.29066 | D100: =F26/AVERAGE(F39,F25) -> 1.1217822 | F100: =J26/AVERAGE(J39,J25) -> 0.99017723 | H100: =N26/AVERAGE(N39,N25) -> 1.4096406 | J100: =R26/AVERAGE(R39,R25) -> 0.98679614 | L100: =AVERAGE(B100:J100) -> 1.1598112
A101: Equity Multiplier | B101: =AVERAGE(B39,B25)/AVERAGE(B38,B24) -> 1.4746142 | D101: =AVERAGE(F39,F25)/AVERAGE(F38,F24) -> 1.4136229 | F101: =AVERAGE(J39,J25)/AVERAGE(J38,J24) -> 1.3140316 | H101: =AVERAGE(N39,N25)/AVERAGE(N38,N24) -> 2.1839046 | J101: =AVERAGE(R39,R25)/AVERAGE(R38,R24) -> 1.2641316 | L101: =AVERAGE(B101:J101) -> 1.530061
A102: ROE (product) | B102: =B99*B100*B101 -> 0.20166007 | D102: =D99*D100*D101 -> 0.19236245 | F102: =F99*F100*F101 -> 0.14663739 | H102: =H99*H100*H101 -> 0.32251025 | J102: =J99*J100*J101 -> 0.16993265 | L102: =L99*L100*L101 -> 0.20618829
A104: FY2025-26
B105: Berger Paints | D105: Asian Paints | F105: Indigo Paints | H105: JSW Dulux (fmrly Akzo Nobel India) | J105: Kansai Nerolac | L105: Industry Avg (5 companies)
A106: Net Profit Margin | B106: =D30/D26 -> 0.1051487 | D106: =H30/H26 -> 0.13793441 | F106: =L30/L26 -> 0.10930593 | H106: =P30/P26 -> 0.53281285 | J106: =T30/T26 -> 0.080091947 | L106: =AVERAGE(B106:J106) -> 0.19305877
A107: Asset Turnover | B107: =D26/AVERAGE(B25,D25) -> 1.2171087 | D107: =H26/AVERAGE(F25,H25) -> 1.0846283 | F107: =L26/AVERAGE(J25,L25) -> 0.90864501 | H107: =P26/AVERAGE(N25,P25) -> 1.0857315 | J107: =T26/AVERAGE(R25,T25) -> 0.93764353 | L107: =AVERAGE(B107:J107) -> 1.0467514
A108: Equity Multiplier | B108: =AVERAGE(B25,D25)/AVERAGE(B24,D24) -> 1.4240491 | D108: =AVERAGE(F25,H25)/AVERAGE(F24,H24) -> 1.4268154 | F108: =AVERAGE(J25,L25)/AVERAGE(J24,L24) -> 1.3125815 | H108: =AVERAGE(N25,P25)/AVERAGE(N24,P24) -> 1.7808698 | J108: =AVERAGE(R25,T25)/AVERAGE(R24,T24) -> 1.2638057 | L108: =AVERAGE(B108:J108) -> 1.4416243
A109: ROE (product) | B109: =B106*B107*B108 -> 0.18224612 | D109: =D106*D107*D108 -> 0.21346238 | F109: =F106*F107*F108 -> 0.13036597 | H109: =H106*H107*H108 -> 1.0302184 | J109: =J106*J107*J108 -> 0.094908896 | L109: =L106*L107*L108 -> 0.29132998
A111: 6. 5-Factor DuPont Analysis - ROE Decomposition, FY2024-25 & FY2025-26
A112: Each company's own worksheet now carries a 5-Factor DuPont Analysis (Tax Burden × Interest Burden × EBIT Margin × Asset Turnover × Equity Multiplier) in addition to the 3-factor DuPont analysis in Section 5 above; see each company sheet for the full methodology note. EBIT is defined as Profit Before Tax (PBT) + Finance Costs, which makes the five-factor product reconcile exactly to the directly-computed ROE already shown in Section 5 - re-verified below to reconcile to at least six decimal places for all five companies and both fiscal years. All figures below are live formulas calculated on this sheet from the local book-value tables in section 1 at the top of the sheet. Column G (“Industry Avg (5 companies)”) averages each factor across all five companies; the Industry Avg 5-Factor product is the product of those five averaged factors and, by construction, does not equal the average of the five companies' ROEs - its reconciliation difference is genuine and is not forced to zero.
A114: FY2024-25
B115: Berger Paints | D115: Asian Paints | F115: Indigo Paints | H115: JSW Dulux | J115: Kansai Nerolac | L115: Industry Avg (5 companies)
A116: Tax Burden | B116: =B30/B28 -> 0.75310678 | D116: =F30/F28 -> 0.73202945 | F116: =J30/J28 -> 0.74879051 | H116: =N30/N28 -> 0.75232579 | J116: =R30/R28 -> 0.73650125 | L116: =AVERAGE(B116:J116) -> 0.74455076
A117: Interest Burden | B117: =B28/(B28+B35) -> 0.96763154 | D117: =F28/(F28+F35) -> 0.97147958 | F117: =J28/(J28+J35) -> 0.98483529 | H117: =N28/(N28+N35) -> 0.98308887 | J117: =R28/(R28+R35) -> 0.9892345 | L117: =AVERAGE(B117:J117) -> 0.97925396
A118: EBIT Margin | B118: =(B28+B35)/B26 -> 0.14539955 | D118: =(F28+F35)/F26 -> 0.17057523 | F118: =(J28+J35)/J26 -> 0.15282769 | H118: =(N28+N35)/N26 -> 0.14164548 | J118: =(R28+R35)/R26 -> 0.18697535 | L118: =AVERAGE(B118:J118) -> 0.15948466
A119: Asset Turnover | B119: =B100 -> 1.29066 | D119: =D100 -> 1.1217822 | F119: =F100 -> 0.99017723 | H119: =H100 -> 1.4096406 | J119: =J100 -> 0.98679614 | L119: =AVERAGE(B119:J119) -> 1.1598112
A120: Equity Multiplier | B120: =B101 -> 1.4746142 | D120: =D101 -> 1.4136229 | F120: =F101 -> 1.3140316 | H120: =H101 -> 2.1839046 | J120: =J101 -> 1.2641316 | L120: =AVERAGE(B120:J120) -> 1.530061
A121: 5-Factor DuPont ROE (product) | B121: =B116*B117*B118*B119*B120 -> 0.20166007 | D121: =D116*D117*D118*D119*D120 -> 0.19236245 | F121: =F116*F117*F118*F119*F120 -> 0.14663739 | H121: =H116*H117*H118*H119*H120 -> 0.32251025 | J121: =J116*J117*J118*J119*J120 -> 0.16993265 | L121: =L116*L117*L118*L119*L120 -> 0.20635007
A122: Directly-Calculated ROE (existing) | B122: =B53 -> 0.20166007 | D122: =D53 -> 0.19236245 | F122: =F53 -> 0.14663739 | H122: =H53 -> 0.32251025 | J122: =J53 -> 0.16993265 | L122: =AVERAGE(B122:J122) -> 0.20662056
A123: Reconciliation Difference | B123: =B121-B122 -> 0 | D123: =D121-D122 -> 0 | F123: =F121-F122 -> 0 | H123: =H121-H122 -> 0 | J123: =J121-J122 -> 0 | L123: =L121-L122 -> -0.00027049493
A125: FY2025-26
B126: Berger Paints | D126: Asian Paints | F126: Indigo Paints | H126: JSW Dulux | J126: Kansai Nerolac | L126: Industry Avg (5 companies)
A127: Tax Burden | B127: =D30/D28 -> 0.76181669 | D127: =H30/H28 -> 0.74022778 | F127: =L30/L28 -> 0.74455882 | H127: =P30/P28 -> 0.83389138 | J127: =T30/T28 -> 0.73949249 | L127: =AVERAGE(B127:J127) -> 0.76399743
A128: Interest Burden | B128: =D28/(D28+D35) -> 0.96926851 | D128: =H28/(H28+H35) -> 0.97827144 | F128: =L28/(L28+L35) -> 0.98790853 | H128: =P28/(P28+P35) -> 0.99476598 | J128: =T28/(T28+T35) -> 0.97850856 | L128: =AVERAGE(B128:J128) -> 0.9817446
A129: EBIT Margin | B129: =(D28+D35)/D26 -> 0.14239979 | D129: =(H28+H35)/H26 -> 0.19047933 | F129: =(L28+L35)/L26 -> 0.14860313 | H129: =(P28+P35)/P26 -> 0.6423094 | J129: =(T28+T35)/T26 -> 0.11068543 | L129: =AVERAGE(B129:J129) -> 0.24689542
A130: Asset Turnover | B130: =B107 -> 1.2171087 | D130: =D107 -> 1.0846283 | F130: =F107 -> 0.90864501 | H130: =H107 -> 1.0857315 | J130: =J107 -> 0.93764353 | L130: =AVERAGE(B130:J130) -> 1.0467514
A131: Equity Multiplier | B131: =B108 -> 1.4240491 | D131: =D108 -> 1.4268154 | F131: =F108 -> 1.3125815 | H131: =H108 -> 1.7808698 | J131: =J108 -> 1.2638057 | L131: =AVERAGE(B131:J131) -> 1.4416243
A132: 5-Factor DuPont ROE (product) | B132: =B127*B128*B129*B130*B131 -> 0.18224612 | D132: =D127*D128*D129*D130*D131 -> 0.21346238 | F132: =F127*F128*F129*F130*F131 -> 0.13036597 | H132: =H127*H128*H129*H130*H131 -> 1.0302184 | J132: =J127*J128*J129*J130*J131 -> 0.094908896 | L132: =L127*L128*L129*L130*L131 -> 0.27944678
...
